{
  "beans" : [ {
    "name" : "java.lang:type=MemoryPool,name=CMS Old Gen",
    "modelerType" : "sun.management.MemoryPoolImpl",
    "Name" : "CMS Old Gen",
    "Type" : "HEAP",
    "Valid" : true,
    "Usage" : {
      "committed" : 3457503232,
      "init" : 697499648,
      "max" : 7717519360,
      "used" : 2451682056
    },
    "PeakUsage" : {
      "committed" : 3457503232,
      "init" : 697499648,
      "max" : 7717519360,
      "used" : 3227318552
    },
    "MemoryManagerNames" : [ "ConcurrentMarkSweep" ],
    "UsageThreshold" : 0,
    "UsageThresholdExceeded" : false,
    "UsageThresholdCount" : 0,
    "UsageThresholdSupported" : true,
    "CollectionUsageThreshold" : 0,
    "CollectionUsageThresholdExceeded" : false,
    "CollectionUsageThresholdCount" : 0,
    "CollectionUsage" : {
      "committed" : 3457503232,
      "init" : 697499648,
      "max" : 7717519360,
      "used" : 1819514200
    },
    "CollectionUsageThresholdSupported" : true
  }, {
    "name" : "java.lang:type=Memory",
    "modelerType" : "sun.management.MemoryImpl",
    "HeapMemoryUsage" : {
      "committed" : 3771355136,
      "init" : 1046160640,
      "max" : 8502706176,
      "used" : 2698980048
    },
    "Verbose" : false,
    "ObjectPendingFinalizationCount" : 0,
    "NonHeapMemoryUsage" : {
      "committed" : 44503040,
      "init" : 24313856,
      "max" : 224395264,
      "used" : 29392960
    }
  }, {
    "name" : "hadoop:service=HBase,name=RPCStatistics-60020",
    "modelerType" : "org.apache.hadoop.hbase.ipc.HBaseRPCStatistics",
    "enableTableNumOps" : 0,
    "enableTableAvgTime" : 0,
    "enableTableMinTime" : -1,
    "enableTableMaxTime" : 0,
    "assignNumOps" : 0,
    "assignAvgTime" : 0,
    "assignMinTime" : -1,
    "assignMaxTime" : 0,
    "flushRegion.aboveOneSec.NumOps" : 0,
    "flushRegion.aboveOneSec.AvgTime" : 0,
    "flushRegion.aboveOneSec.MinTime" : -1,
    "flushRegion.aboveOneSec.MaxTime" : 0,
    "incrementColumnValue.aboveOneSec.NumOps" : 0,
    "incrementColumnValue.aboveOneSec.AvgTime" : 0,
    "incrementColumnValue.aboveOneSec.MinTime" : -1,
    "incrementColumnValue.aboveOneSec.MaxTime" : 0,
    "getZooKeeper.aboveOneSec.NumOps" : 0,
    "getZooKeeper.aboveOneSec.AvgTime" : 0,
    "getZooKeeper.aboveOneSec.MinTime" : -1,
    "getZooKeeper.aboveOneSec.MaxTime" : 0,
    "splitRegion.aboveOneSec.NumOps" : 0,
    "splitRegion.aboveOneSec.AvgTime" : 0,
    "splitRegion.aboveOneSec.MinTime" : -1,
    "splitRegion.aboveOneSec.MaxTime" : 0,
    "RpcSlowResponseNumOps" : 0,
    "RpcSlowResponseAvgTime" : 0,
    "RpcSlowResponseMinTime" : -1,
    "RpcSlowResponseMaxTime" : 0,
    "getStoreFileListNumOps" : 0,
    "getStoreFileListAvgTime" : 0,
    "getStoreFileListMinTime" : -1,
    "getStoreFileListMaxTime" : 0,
    "getProtocolVersion.aboveOneSec.NumOps" : 0,
    "getProtocolVersion.aboveOneSec.AvgTime" : 0,
    "getProtocolVersion.aboveOneSec.MinTime" : -1,
    "getProtocolVersion.aboveOneSec.MaxTime" : 0,
    "getCatalogTracker.aboveOneSec.NumOps" : 0,
    "getCatalogTracker.aboveOneSec.AvgTime" : 0,
    "getCatalogTracker.aboveOneSec.MinTime" : -1,
    "getCatalogTracker.aboveOneSec.MaxTime" : 0,
    "rollHLogWriter.aboveOneSec.NumOps" : 0,
    "rollHLogWriter.aboveOneSec.AvgTime" : 0,
    "rollHLogWriter.aboveOneSec.MinTime" : -1,
    "rollHLogWriter.aboveOneSec.MaxTime" : 0,
    "restoreSnapshotNumOps" : 0,
    "restoreSnapshotAvgTime" : 0,
    "restoreSnapshotMinTime" : -1,
    "restoreSnapshotMaxTime" : 0,
    "bulkLoadHFiles.aboveOneSec.NumOps" : 0,
    "bulkLoadHFiles.aboveOneSec.AvgTime" : 0,
    "bulkLoadHFiles.aboveOneSec.MinTime" : -1,
    "bulkLoadHFiles.aboveOneSec.MaxTime" : 0,
    "delete.aboveOneSec.NumOps" : 0,
    "delete.aboveOneSec.AvgTime" : 0,
    "delete.aboveOneSec.MinTime" : -1,
    "delete.aboveOneSec.MaxTime" : 0,
    "moveNumOps" : 0,
    "moveAvgTime" : 0,
    "moveMinTime" : -1,
    "moveMaxTime" : 0,
    "getServerNameNumOps" : 0,
    "getServerNameAvgTime" : 0,
    "getServerNameMinTime" : -1,
    "getServerNameMaxTime" : 0,
    "openRegionNumOps" : 0,
    "openRegionAvgTime" : 0,
    "openRegionMinTime" : 7,
    "openRegionMaxTime" : 132,
    "getClosestRowBefore.aboveOneSec.NumOps" : 0,
    "getClosestRowBefore.aboveOneSec.AvgTime" : 0,
    "getClosestRowBefore.aboveOneSec.MinTime" : -1,
    "getClosestRowBefore.aboveOneSec.MaxTime" : 0,
    "addToOnlineRegionsNumOps" : 0,
    "addToOnlineRegionsAvgTime" : 0,
    "addToOnlineRegionsMinTime" : -1,
    "addToOnlineRegionsMaxTime" : 0,
    "incrementNumOps" : 0,
    "incrementAvgTime" : 0,
    "incrementMinTime" : -1,
    "incrementMaxTime" : 0,
    "increment.aboveOneSec.NumOps" : 0,
    "increment.aboveOneSec.AvgTime" : 0,
    "increment.aboveOneSec.MinTime" : -1,
    "increment.aboveOneSec.MaxTime" : 0,
    "deleteTableNumOps" : 0,
    "deleteTableAvgTime" : 0,
    "deleteTableMinTime" : -1,
    "deleteTableMaxTime" : 0,
    "execCoprocessor.aboveOneSec.NumOps" : 0,
    "execCoprocessor.aboveOneSec.AvgTime" : 0,
    "execCoprocessor.aboveOneSec.MinTime" : -1,
    "execCoprocessor.aboveOneSec.MaxTime" : 0,
    "checkOOME.aboveOneSec.NumOps" : 0,
    "checkOOME.aboveOneSec.AvgTime" : 0,
    "checkOOME.aboveOneSec.MinTime" : -1,
    "checkOOME.aboveOneSec.MaxTime" : 0,
    "get.aboveOneSec.NumOps" : 0,
    "get.aboveOneSec.AvgTime" : 0,
    "get.aboveOneSec.MinTime" : -1,
    "get.aboveOneSec.MaxTime" : 0,
    "getCatalogTrackerNumOps" : 0,
    "getCatalogTrackerAvgTime" : 0,
    "getCatalogTrackerMinTime" : -1,
    "getCatalogTrackerMaxTime" : 0,
    "getHServerInfo.aboveOneSec.NumOps" : 0,
    "getHServerInfo.aboveOneSec.AvgTime" : 0,
    "getHServerInfo.aboveOneSec.MinTime" : -1,
    "getHServerInfo.aboveOneSec.MaxTime" : 0,
    "execCoprocessorNumOps" : 0,
    "execCoprocessorAvgTime" : 0,
    "execCoprocessorMinTime" : -1,
    "execCoprocessorMaxTime" : 0,
    "openRegions.aboveOneSec.NumOps" : 0,
    "openRegions.aboveOneSec.AvgTime" : 0,
    "openRegions.aboveOneSec.MinTime" : 2121,
    "openRegions.aboveOneSec.MaxTime" : 2121,
    "openScanner.aboveOneSec.NumOps" : 0,
    "openScanner.aboveOneSec.AvgTime" : 0,
    "openScanner.aboveOneSec.MinTime" : -1,
    "openScanner.aboveOneSec.MaxTime" : 0,
    "getHTableDescriptorsNumOps" : 0,
    "getHTableDescriptorsAvgTime" : 0,
    "getHTableDescriptorsMinTime" : -1,
    "getHTableDescriptorsMaxTime" : 0,
    "getLastFlushTime.aboveOneSec.NumOps" : 0,
    "getLastFlushTime.aboveOneSec.AvgTime" : 0,
    "getLastFlushTime.aboveOneSec.MinTime" : -1,
    "getLastFlushTime.aboveOneSec.MaxTime" : 0,
    "addColumnNumOps" : 0,
    "addColumnAvgTime" : 0,
    "addColumnMinTime" : -1,
    "addColumnMaxTime" : 0,
    "abort.aboveOneSec.NumOps" : 0,
    "abort.aboveOneSec.AvgTime" : 0,
    "abort.aboveOneSec.MinTime" : -1,
    "abort.aboveOneSec.MaxTime" : 0,
    "getServerName.aboveOneSec.NumOps" : 0,
    "getServerName.aboveOneSec.AvgTime" : 0,
    "getServerName.aboveOneSec.MinTime" : -1,
    "getServerName.aboveOneSec.MaxTime" : 0,
    "multiNumOps" : 3,
    "multiAvgTime" : 1,
    "multiMinTime" : 0,
    "multiMaxTime" : 3577,
    "closeRegionNumOps" : 0,
    "closeRegionAvgTime" : 0,
    "closeRegionMinTime" : -1,
    "closeRegionMaxTime" : 0,
    "disableTableNumOps" : 0,
    "disableTableAvgTime" : 0,
    "disableTableMinTime" : -1,
    "disableTableMaxTime" : 0,
    "next.aboveOneSec.NumOps" : 0,
    "next.aboveOneSec.AvgTime" : 0,
    "next.aboveOneSec.MinTime" : -1,
    "next.aboveOneSec.MaxTime" : 0,
    "bulkLoadHFilesNumOps" : 0,
    "bulkLoadHFilesAvgTime" : 0,
    "bulkLoadHFilesMinTime" : -1,
    "bulkLoadHFilesMaxTime" : 0,
    "putNumOps" : 0,
    "putAvgTime" : 0,
    "putMinTime" : -1,
    "putMaxTime" : 0,
    "createTableNumOps" : 0,
    "createTableAvgTime" : 0,
    "createTableMinTime" : -1,
    "createTableMaxTime" : 0,
    "stop.aboveOneSec.NumOps" : 0,
    "stop.aboveOneSec.AvgTime" : 0,
    "stop.aboveOneSec.MinTime" : -1,
    "stop.aboveOneSec.MaxTime" : 0,
    "nextNumOps" : 711,
    "nextAvgTime" : 0,
    "nextMinTime" : 0,
    "nextMaxTime" : 35,
    "unlockRowNumOps" : 0,
    "unlockRowAvgTime" : 0,
    "unlockRowMinTime" : -1,
    "unlockRowMaxTime" : 0,
    "reportRSFatalErrorNumOps" : 0,
    "reportRSFatalErrorAvgTime" : 0,
    "reportRSFatalErrorMinTime" : -1,
    "reportRSFatalErrorMaxTime" : 0,
    "rpcAuthenticationFailures" : 0,
    "getRegionInfoNumOps" : 0,
    "getRegionInfoAvgTime" : 0,
    "getRegionInfoMinTime" : 0,
    "getRegionInfoMaxTime" : 0,
    "openScannerNumOps" : 657,
    "openScannerAvgTime" : 0,
    "openScannerMinTime" : 0,
    "openScannerMaxTime" : 45,
    "offlineNumOps" : 0,
    "offlineAvgTime" : 0,
    "offlineMinTime" : -1,
    "offlineMaxTime" : 0,
    "getStoreFileList.aboveOneSec.NumOps" : 0,
    "getStoreFileList.aboveOneSec.AvgTime" : 0,
    "getStoreFileList.aboveOneSec.MinTime" : -1,
    "getStoreFileList.aboveOneSec.MaxTime" : 0,
    "getAlterStatusNumOps" : 0,
    "getAlterStatusAvgTime" : 0,
    "getAlterStatusMinTime" : -1,
    "getAlterStatusMaxTime" : 0,
    "deleteNumOps" : 0,
    "deleteAvgTime" : 0,
    "deleteMinTime" : -1,
    "deleteMaxTime" : 0,
    "getFromOnlineRegionsNumOps" : 0,
    "getFromOnlineRegionsAvgTime" : 0,
    "getFromOnlineRegionsMinTime" : -1,
    "getFromOnlineRegionsMaxTime" : 0,
    "RpcProcessingTimeNumOps" : 2026,
    "RpcProcessingTimeAvgTime" : 0,
    "RpcProcessingTimeMinTime" : 0,
    "RpcProcessingTimeMaxTime" : 3577,
    "isStoppedNumOps" : 0,
    "isStoppedAvgTime" : 0,
    "isStoppedMinTime" : -1,
    "isStoppedMaxTime" : 0,
    "getLastFlushTimeNumOps" : 0,
    "getLastFlushTimeAvgTime" : 0,
    "getLastFlushTimeMinTime" : -1,
    "getLastFlushTimeMaxTime" : 0,
    "shutdownNumOps" : 0,
    "shutdownAvgTime" : 0,
    "shutdownMinTime" : -1,
    "shutdownMaxTime" : 0,
    "openRegionsNumOps" : 0,
    "openRegionsAvgTime" : 0,
    "openRegionsMinTime" : 2121,
    "openRegionsMaxTime" : 2121,
    "getClosestRowBeforeNumOps" : 0,
    "getClosestRowBeforeAvgTime" : 0,
    "getClosestRowBeforeMinTime" : 0,
    "getClosestRowBeforeMaxTime" : 5,
    "deleteSnapshotNumOps" : 0,
    "deleteSnapshotAvgTime" : 0,
    "deleteSnapshotMinTime" : -1,
    "deleteSnapshotMaxTime" : 0,
    "getHServerInfoNumOps" : 0,
    "getHServerInfoAvgTime" : 0,
    "getHServerInfoMinTime" : -1,
    "getHServerInfoMaxTime" : 0,
    "getProtocolSignatureNumOps" : 0,
    "getProtocolSignatureAvgTime" : 0,
    "getProtocolSignatureMinTime" : -1,
    "getProtocolSignatureMaxTime" : 0,
    "replicationCallQueueLen" : 0,
    "snapshotNumOps" : 0,
    "snapshotAvgTime" : 0,
    "snapshotMinTime" : -1,
    "snapshotMaxTime" : 0,
    "getRegionInfo.aboveOneSec.NumOps" : 0,
    "getRegionInfo.aboveOneSec.AvgTime" : 0,
    "getRegionInfo.aboveOneSec.MinTime" : -1,
    "getRegionInfo.aboveOneSec.MaxTime" : 0,
    "getZooKeeperNumOps" : 0,
    "getZooKeeperAvgTime" : 0,
    "getZooKeeperMinTime" : -1,
    "getZooKeeperMaxTime" : 0,
    "getOnlineRegions.aboveOneSec.NumOps" : 0,
    "getOnlineRegions.aboveOneSec.AvgTime" : 0,
    "getOnlineRegions.aboveOneSec.MinTime" : -1,
    "getOnlineRegions.aboveOneSec.MaxTime" : 0,
    "append.aboveOneSec.NumOps" : 0,
    "append.aboveOneSec.AvgTime" : 0,
    "append.aboveOneSec.MinTime" : -1,
    "append.aboveOneSec.MaxTime" : 0,
    "removeFromOnlineRegions.aboveOneSec.NumOps" : 0,
    "removeFromOnlineRegions.aboveOneSec.AvgTime" : 0,
    "removeFromOnlineRegions.aboveOneSec.MinTime" : -1,
    "removeFromOnlineRegions.aboveOneSec.MaxTime" : 0,
    "SentBytes" : 51650,
    "existsNumOps" : 0,
    "existsAvgTime" : 0,
    "existsMinTime" : -1,
    "existsMaxTime" : 0,
    "getFromOnlineRegions.aboveOneSec.NumOps" : 0,
    "getFromOnlineRegions.aboveOneSec.AvgTime" : 0,
    "getFromOnlineRegions.aboveOneSec.MinTime" : -1,
    "getFromOnlineRegions.aboveOneSec.MaxTime" : 0,
    "unlockRow.aboveOneSec.NumOps" : 0,
    "unlockRow.aboveOneSec.AvgTime" : 0,
    "unlockRow.aboveOneSec.MinTime" : -1,
    "unlockRow.aboveOneSec.MaxTime" : 0,
    "activeRpcCount" : 0,
    "isStopped.aboveOneSec.NumOps" : 0,
    "isStopped.aboveOneSec.AvgTime" : 0,
    "isStopped.aboveOneSec.MinTime" : -1,
    "isStopped.aboveOneSec.MaxTime" : 0,
    "getCompletedSnapshotsNumOps" : 0,
    "getCompletedSnapshotsAvgTime" : 0,
    "getCompletedSnapshotsMinTime" : -1,
    "getCompletedSnapshotsMaxTime" : 0,
    "regionServerStartupNumOps" : 0,
    "regionServerStartupAvgTime" : 0,
    "regionServerStartupMinTime" : -1,
    "regionServerStartupMaxTime" : 0,
    "compactRegionNumOps" : 0,
    "compactRegionAvgTime" : 0,
    "compactRegionMinTime" : -1,
    "compactRegionMaxTime" : 0,
    "abortNumOps" : 0,
    "abortAvgTime" : 0,
    "abortMinTime" : -1,
    "abortMaxTime" : 0,
    "balanceSwitchNumOps" : 0,
    "balanceSwitchAvgTime" : 0,
    "balanceSwitchMinTime" : -1,
    "balanceSwitchMaxTime" : 0,
    "rollHLogWriterNumOps" : 0,
    "rollHLogWriterAvgTime" : 0,
    "rollHLogWriterMinTime" : -1,
    "rollHLogWriterMaxTime" : 0,
    "splitRegionNumOps" : 0,
    "splitRegionAvgTime" : 0,
    "splitRegionMinTime" : -1,
    "splitRegionMaxTime" : 0,
    "ReceivedBytes" : 188056,
    "isSnapshotDoneNumOps" : 0,
    "isSnapshotDoneAvgTime" : 0,
    "isSnapshotDoneMinTime" : -1,
    "isSnapshotDoneMaxTime" : 0,
    "getOnlineRegionsNumOps" : 0,
    "getOnlineRegionsAvgTime" : 0,
    "getOnlineRegionsMinTime" : -1,
    "getOnlineRegionsMaxTime" : 0,
    "closeNumOps" : 655,
    "closeAvgTime" : 0,
    "closeMinTime" : 0,
    "closeMaxTime" : 13,
    "balanceNumOps" : 0,
    "balanceAvgTime" : 0,
    "balanceMinTime" : -1,
    "balanceMaxTime" : 0,
    "getProtocolSignature.aboveOneSec.NumOps" : 0,
    "getProtocolSignature.aboveOneSec.AvgTime" : 0,
    "getProtocolSignature.aboveOneSec.MinTime" : -1,
    "getProtocolSignature.aboveOneSec.MaxTime" : 0,
    "openRegion.aboveOneSec.NumOps" : 0,
    "openRegion.aboveOneSec.AvgTime" : 0,
    "openRegion.aboveOneSec.MinTime" : -1,
    "openRegion.aboveOneSec.MaxTime" : 0,
    "isAborted.aboveOneSec.NumOps" : 0,
    "isAborted.aboveOneSec.AvgTime" : 0,
    "isAborted.aboveOneSec.MinTime" : -1,
    "isAborted.aboveOneSec.MaxTime" : 0,
    "getClusterStatusNumOps" : 0,
    "getClusterStatusAvgTime" : 0,
    "getClusterStatusMinTime" : -1,
    "getClusterStatusMaxTime" : 0,
    "isAbortedNumOps" : 0,
    "isAbortedAvgTime" : 0,
    "isAbortedMinTime" : -1,
    "isAbortedMaxTime" : 0,
    "exists.aboveOneSec.NumOps" : 0,
    "exists.aboveOneSec.AvgTime" : 0,
    "exists.aboveOneSec.MinTime" : -1,
    "exists.aboveOneSec.MaxTime" : 0,
    "lockRow.aboveOneSec.NumOps" : 0,
    "lockRow.aboveOneSec.AvgTime" : 0,
    "lockRow.aboveOneSec.MinTime" : -1,
    "lockRow.aboveOneSec.MaxTime" : 0,
    "appendNumOps" : 0,
    "appendAvgTime" : 0,
    "appendMinTime" : -1,
    "appendMaxTime" : 0,
    "getBlockCacheColumnFamilySummariesNumOps" : 0,
    "getBlockCacheColumnFamilySummariesAvgTime" : 0,
    "getBlockCacheColumnFamilySummariesMinTime" : -1,
    "getBlockCacheColumnFamilySummariesMaxTime" : 0,
    "synchronousBalanceSwitchNumOps" : 0,
    "synchronousBalanceSwitchAvgTime" : 0,
    "synchronousBalanceSwitchMinTime" : -1,
    "synchronousBalanceSwitchMaxTime" : 0,
    "getConfiguration.aboveOneSec.NumOps" : 0,
    "getConfiguration.aboveOneSec.AvgTime" : 0,
    "getConfiguration.aboveOneSec.MinTime" : -1,
    "getConfiguration.aboveOneSec.MaxTime" : 0,
    "getNumOps" : 0,
    "getAvgTime" : 0,
    "getMinTime" : 0,
    "getMaxTime" : 48,
    "stopMasterNumOps" : 0,
    "stopMasterAvgTime" : 0,
    "stopMasterMinTime" : -1,
    "stopMasterMaxTime" : 0,
    "priorityCallQueueLen" : 0,
    "closeRegion.aboveOneSec.NumOps" : 0,
    "closeRegion.aboveOneSec.AvgTime" : 0,
    "closeRegion.aboveOneSec.MinTime" : -1,
    "closeRegion.aboveOneSec.MaxTime" : 0,
    "getCompactionState.aboveOneSec.NumOps" : 0,
    "getCompactionState.aboveOneSec.AvgTime" : 0,
    "getCompactionState.aboveOneSec.MinTime" : -1,
    "getCompactionState.aboveOneSec.MaxTime" : 0,
    "put.aboveOneSec.NumOps" : 0,
    "put.aboveOneSec.AvgTime" : 0,
    "put.aboveOneSec.MinTime" : -1,
    "put.aboveOneSec.MaxTime" : 0,
    "checkAndPutNumOps" : 0,
    "checkAndPutAvgTime" : 0,
    "checkAndPutMinTime" : 0,
    "checkAndPutMaxTime" : 4,
    "addToOnlineRegions.aboveOneSec.NumOps" : 0,
    "addToOnlineRegions.aboveOneSec.AvgTime" : 0,
    "addToOnlineRegions.aboveOneSec.MinTime" : -1,
    "addToOnlineRegions.aboveOneSec.MaxTime" : 0,
    "deleteColumnNumOps" : 0,
    "deleteColumnAvgTime" : 0,
    "deleteColumnMinTime" : -1,
    "deleteColumnMaxTime" : 0,
    "checkAndDelete.aboveOneSec.NumOps" : 0,
    "checkAndDelete.aboveOneSec.AvgTime" : 0,
    "checkAndDelete.aboveOneSec.MinTime" : -1,
    "checkAndDelete.aboveOneSec.MaxTime" : 0,
    "getBlockCacheColumnFamilySummaries.aboveOneSec.NumOps" : 0,
    "getBlockCacheColumnFamilySummaries.aboveOneSec.AvgTime" : 0,
    "getBlockCacheColumnFamilySummaries.aboveOneSec.MinTime" : -1,
    "getBlockCacheColumnFamilySummaries.aboveOneSec.MaxTime" : 0,
    "callQueueLen" : 0,
    "getConfigurationNumOps" : 0,
    "getConfigurationAvgTime" : 0,
    "getConfigurationMinTime" : -1,
    "getConfigurationMaxTime" : 0,
    "replicateLogEntriesNumOps" : 0,
    "replicateLogEntriesAvgTime" : 0,
    "replicateLogEntriesMinTime" : -1,
    "replicateLogEntriesMaxTime" : 0,
    "checkAndPut.aboveOneSec.NumOps" : 0,
    "checkAndPut.aboveOneSec.AvgTime" : 0,
    "checkAndPut.aboveOneSec.MinTime" : -1,
    "checkAndPut.aboveOneSec.MaxTime" : 0,
    "rpcAuthorizationSuccesses" : 0,
    "stopNumOps" : 0,
    "stopAvgTime" : 0,
    "stopMinTime" : -1,
    "stopMaxTime" : 0,
    "incrementColumnValueNumOps" : 0,
    "incrementColumnValueAvgTime" : 0,
    "incrementColumnValueMinTime" : 1,
    "incrementColumnValueMaxTime" : 8,
    "flushRegionNumOps" : 0,
    "flushRegionAvgTime" : 0,
    "flushRegionMinTime" : -1,
    "flushRegionMaxTime" : 0,
    "removeFromOnlineRegionsNumOps" : 0,
    "removeFromOnlineRegionsAvgTime" : 0,
    "removeFromOnlineRegionsMinTime" : -1,
    "removeFromOnlineRegionsMaxTime" : 0,
    "unassignNumOps" : 0,
    "unassignAvgTime" : 0,
    "unassignMinTime" : -1,
    "unassignMaxTime" : 0,
    "compactRegion.aboveOneSec.NumOps" : 0,
    "compactRegion.aboveOneSec.AvgTime" : 0,
    "compactRegion.aboveOneSec.MinTime" : -1,
    "compactRegion.aboveOneSec.MaxTime" : 0,
    "replicateLogEntries.aboveOneSec.NumOps" : 0,
    "replicateLogEntries.aboveOneSec.AvgTime" : 0,
    "replicateLogEntries.aboveOneSec.MinTime" : -1,
    "replicateLogEntries.aboveOneSec.MaxTime" : 0,
    "multi.aboveOneSec.NumOps" : 0,
    "multi.aboveOneSec.AvgTime" : 0,
    "multi.aboveOneSec.MinTime" : 1002,
    "multi.aboveOneSec.MaxTime" : 3577,
    "NumOpenConnections" : 1,
    "rpcAuthenticationSuccesses" : 0,
    "mutateRowNumOps" : 0,
    "mutateRowAvgTime" : 0,
    "mutateRowMinTime" : -1,
    "mutateRowMaxTime" : 0,
    "close.aboveOneSec.NumOps" : 0,
    "close.aboveOneSec.AvgTime" : 0,
    "close.aboveOneSec.MinTime" : -1,
    "close.aboveOneSec.MaxTime" : 0,
    "modifyTableNumOps" : 0,
    "modifyTableAvgTime" : 0,
    "modifyTableMinTime" : -1,
    "modifyTableMaxTime" : 0,
    "rpcAuthorizationFailures" : 0,
    "checkOOMENumOps" : 0,
    "checkOOMEAvgTime" : 0,
    "checkOOMEMinTime" : -1,
    "checkOOMEMaxTime" : 0,
    "getTableNamesNumOps" : 0,
    "getTableNamesAvgTime" : 0,
    "getTableNamesMinTime" : -1,
    "getTableNamesMaxTime" : 0,
    "getProtocolVersionNumOps" : 0,
    "getProtocolVersionAvgTime" : 0,
    "getProtocolVersionMinTime" : 0,
    "getProtocolVersionMaxTime" : 0,
    "RpcQueueTimeNumOps" : 2026,
    "RpcQueueTimeAvgTime" : 0,
    "RpcQueueTimeMinTime" : 0,
    "RpcQueueTimeMaxTime" : 61,
    "checkAndDeleteNumOps" : 0,
    "checkAndDeleteAvgTime" : 0,
    "checkAndDeleteMinTime" : -1,
    "checkAndDeleteMaxTime" : 0,
    "scan.aboveOneSec.NumOps" : 0,
    "scan.aboveOneSec.AvgTime" : 0,
    "scan.aboveOneSec.MinTime" : -1,
    "scan.aboveOneSec.MaxTime" : 0,
    "modifyColumnNumOps" : 0,
    "modifyColumnAvgTime" : 0,
    "modifyColumnMinTime" : -1,
    "modifyColumnMaxTime" : 0,
    "isMasterRunningNumOps" : 0,
    "isMasterRunningAvgTime" : 0,
    "isMasterRunningMinTime" : -1,
    "isMasterRunningMaxTime" : 0,
    "lockRowNumOps" : 0,
    "lockRowAvgTime" : 0,
    "lockRowMinTime" : -1,
    "lockRowMaxTime" : 0,
    "isRestoreSnapshotDoneNumOps" : 0,
    "isRestoreSnapshotDoneAvgTime" : 0,
    "isRestoreSnapshotDoneMinTime" : -1,
    "isRestoreSnapshotDoneMaxTime" : 0,
    "scanNumOps" : 0,
    "scanAvgTime" : 0,
    "scanMinTime" : -1,
    "scanMaxTime" : 0,
    "getCompactionStateNumOps" : 0,
    "getCompactionStateAvgTime" : 0,
    "getCompactionStateMinTime" : -1,
    "getCompactionStateMaxTime" : 0,
    "mutateRow.aboveOneSec.NumOps" : 0,
    "mutateRow.aboveOneSec.AvgTime" : 0,
    "mutateRow.aboveOneSec.MinTime" : -1,
    "mutateRow.aboveOneSec.MaxTime" : 0,
    "regionServerReportNumOps" : 0,
    "regionServerReportAvgTime" : 0,
    "regionServerReportMinTime" : -1,
    "regionServerReportMaxTime" : 0
  }, {
    "name" : "hadoop:service=HBase,name=Info",
    "modelerType" : "org.apache.hadoop.hbase.metrics.HBaseInfo$HBaseInfoMBean",
    "revision" : "1577788",
    "hdfsUser" : "hortonfo",
    "hdfsDate" : "Tue May  8 20:31:25 UTC 2012",
    "hdfsUrl" : "https://svn.apache.org/repos/asf/hadoop/common/branches/branch-1.0",
    "date" : "Sat Mar 15 04:46:47 UTC 2014",
    "hdfsRevision" : "1335192",
    "user" : "jenkins",
    "hdfsVersion" : "1.0.3",
    "url" : "https://svn.apache.org/repos/asf/hbase/tags/0.94.18RC0",
    "version" : "0.94.18"
  }, {
    "name" : "java.lang:type=MemoryPool,name=Code Cache",
    "modelerType" : "sun.management.MemoryPoolImpl",
    "Name" : "Code Cache",
    "Type" : "NON_HEAP",
    "Valid" : true,
    "Usage" : {
      "committed" : 5636096,
      "init" : 2555904,
      "max" : 50331648,
      "used" : 5516736
    },
    "PeakUsage" : {
      "committed" : 5636096,
      "init" : 2555904,
      "max" : 50331648,
      "used" : 5526720
    },
    "MemoryManagerNames" : [ "CodeCacheManager" ],
    "UsageThreshold" : 0,
    "UsageThresholdExceeded" : false,
    "UsageThresholdCount" : 0,
    "UsageThresholdSupported" : true,
    "CollectionUsage" : null,
    "CollectionUsageThresholdSupported" : false
  }, {
    "name" : "java.lang:type=Runtime",
    "modelerType" : "sun.management.RuntimeImpl",
    "Name" : "5620@NURSWGHBS001",
    "ClassPath" : "/opt/atsd/hbase/conf:/usr/lib/jvm/java-1.6.0-openjdk-amd64/lib/tools.jar:/opt/atsd/hbase/bin/..:/opt/atsd/hbase/bin/../hbase-0.94.18.jar:/opt/atsd/hbase/bin/../hbase-0.94.18-tests.jar:/opt/atsd/hbase/bin/../lib/activation-1.1.jar:/opt/atsd/hbase/bin/../lib/asm-3.1.jar:/opt/atsd/hbase/bin/../lib/atsd.jar:/opt/atsd/hbase/bin/../lib/avro-1.5.3.jar:/opt/atsd/hbase/bin/../lib/avro-ipc-1.5.3.jar:/opt/atsd/hbase/bin/../lib/commons-beanutils-1.7.0.jar:/opt/atsd/hbase/bin/../lib/commons-beanutils-core-1.8.0.jar:/opt/atsd/hbase/bin/../lib/commons-cli-1.2.jar:/opt/atsd/hbase/bin/../lib/commons-codec-1.4.jar:/opt/atsd/hbase/bin/../lib/commons-collections-3.2.1.jar:/opt/atsd/hbase/bin/../lib/commons-configuration-1.6.jar:/opt/atsd/hbase/bin/../lib/commons-digester-1.8.jar:/opt/atsd/hbase/bin/../lib/commons-el-1.0.jar:/opt/atsd/hbase/bin/../lib/commons-httpclient-3.1.jar:/opt/atsd/hbase/bin/../lib/commons-io-2.1.jar:/opt/atsd/hbase/bin/../lib/commons-lang-2.5.jar:/opt/atsd/hbase/bin/../lib/commons-logging-1.1.1.jar:/opt/atsd/hbase/bin/../lib/commons-math-2.1.jar:/opt/atsd/hbase/bin/../lib/commons-net-1.4.1.jar:/opt/atsd/hbase/bin/../lib/core-3.1.1.jar:/opt/atsd/hbase/bin/../lib/guava-11.0.2.jar:/opt/atsd/hbase/bin/../lib/hadoop-core-1.0.3.jar:/opt/atsd/hbase/bin/../lib/hamcrest-core-1.3.jar:/opt/atsd/hbase/bin/../lib/high-scale-lib-1.1.1.jar:/opt/atsd/hbase/bin/../lib/httpclient-4.1.2.jar:/opt/atsd/hbase/bin/../lib/httpcore-4.1.3.jar:/opt/atsd/hbase/bin/../lib/jackson-core-asl-1.8.8.jar:/opt/atsd/hbase/bin/../lib/jackson-jaxrs-1.8.8.jar:/opt/atsd/hbase/bin/../lib/jackson-mapper-asl-1.8.8.jar:/opt/atsd/hbase/bin/../lib/jackson-xc-1.8.8.jar:/opt/atsd/hbase/bin/../lib/jamon-runtime-2.3.1.jar:/opt/atsd/hbase/bin/../lib/jasper-compiler-5.5.23.jar:/opt/atsd/hbase/bin/../lib/jasper-runtime-5.5.23.jar:/opt/atsd/hbase/bin/../lib/jaxb-api-2.1.jar:/opt/atsd/hbase/bin/../lib/jaxb-impl-2.2.3-1.jar:/opt/atsd/hbase/bin/../lib/jersey-core-1.8.jar:/opt/atsd/hbase/bin/../lib/jersey-json-1.8.jar:/opt/atsd/hbase/bin/../lib/jersey-server-1.8.jar:/opt/atsd/hbase/bin/../lib/jettison-1.1.jar:/opt/atsd/hbase/bin/../lib/jetty-6.1.26.jar:/opt/atsd/hbase/bin/../lib/jetty-util-6.1.26.jar:/opt/atsd/hbase/bin/../lib/jruby-complete-1.6.5.jar:/opt/atsd/hbase/bin/../lib/jsp-2.1-6.1.14.jar:/opt/atsd/hbase/bin/../lib/jsp-api-2.1-6.1.14.jar:/opt/atsd/hbase/bin/../lib/jsr305-1.3.9.jar:/opt/atsd/hbase/bin/../lib/junit-4.11.jar:/opt/atsd/hbase/bin/../lib/libthrift-0.8.0.jar:/opt/atsd/hbase/bin/../lib/log4j-1.2.16.jar:/opt/atsd/hbase/bin/../lib/metrics-core-2.1.2.jar:/opt/atsd/hbase/bin/../lib/netty-3.2.4.Final.jar:/opt/atsd/hbase/bin/../lib/protobuf-java-2.4.0a.jar:/opt/atsd/hbase/bin/../lib/servlet-api-2.5-6.1.14.jar:/opt/atsd/hbase/bin/../lib/slf4j-api-1.4.3.jar:/opt/atsd/hbase/bin/../lib/slf4j-log4j12-1.4.3.jar:/opt/atsd/hbase/bin/../lib/snappy-java-1.0.3.2.jar:/opt/atsd/hbase/bin/../lib/stax-api-1.0.1.jar:/opt/atsd/hbase/bin/../lib/velocity-1.7.jar:/opt/atsd/hbase/bin/../lib/xmlenc-0.52.jar:/opt/atsd/hbase/bin/../lib/zookeeper-3.4.5.jar:",
    "StartTime" : 1437465981016,
    "VmName" : "OpenJDK 64-Bit Server VM",
    "VmVendor" : "Sun Microsystems Inc.",
    "VmVersion" : "23.25-b01",
    "InputArguments" : [ "-XX:OnOutOfMemoryError=kill -9 %p", "-Xmx8192m", "-XX:+UseConcMarkSweepGC", "-Dhbase.log.dir=/opt/atsd/hbase/bin/../logs", "-Dhbase.log.file=hbase-axibase-regionserver-NURSWGHBS001.log", "-Dhbase.home.dir=/opt/atsd/hbase/bin/..", "-Dhbase.id.str=axibase", "-Dhbase.root.logger=INFO,RFA", "-Djava.library.path=/opt/atsd/hbase/bin/../lib/native/Linux-amd64-64", "-Dhbase.security.logger=INFO,DRFAS" ],
    "SpecName" : "Java Virtual Machine Specification",
    "BootClassPathSupported" : true,
    "LibraryPath" : "/opt/atsd/hbase/bin/../lib/native/Linux-amd64-64",
    "BootClassPath" : "/usr/lib/jvm/java-6-openjdk-amd64/jre/lib/resources.jar:/usr/lib/jvm/java-6-openjdk-amd64/jre/lib/rt.jar:/usr/lib/jvm/java-6-openjdk-amd64/jre/lib/sunrsasign.jar:/usr/lib/jvm/java-6-openjdk-amd64/jre/lib/jsse.jar:/usr/lib/jvm/java-6-openjdk-amd64/jre/lib/jce.jar:/usr/lib/jvm/java-6-openjdk-amd64/jre/lib/charsets.jar:/usr/lib/jvm/java-6-openjdk-amd64/jre/lib/jfr.jar:/usr/lib/jvm/java-6-openjdk-amd64/jre/lib/netx.jar:/usr/lib/jvm/java-6-openjdk-amd64/jre/lib/plugin.jar:/usr/lib/jvm/java-6-openjdk-amd64/jre/lib/rhino.jar:/usr/lib/jvm/java-6-openjdk-amd64/jre/classes",
    "ManagementSpecVersion" : "1.2",
    "SpecVendor" : "Sun Microsystems Inc.",
    "SpecVersion" : "1.0",
    "Uptime" : 3881552,
    "SystemProperties" : [ {
      "key" : "java.ext.dirs",
      "value" : "/usr/lib/jvm/java-6-openjdk-amd64/jre/lib/ext:/usr/java/packages/lib/ext"
    }, {
      "key" : "java.vm.specification.vendor",
      "value" : "Sun Microsystems Inc."
    }, {
      "key" : "hbase.log.dir",
      "value" : "/opt/atsd/hbase/bin/../logs"
    }, {
      "key" : "user.timezone",
      "value" : "Europe/Berlin"
    }, {
      "key" : "java.vm.vendor",
      "value" : "Sun Microsystems Inc."
    }, {
      "key" : "user.name",
      "value" : "axibase"
    }, {
      "key" : "java.vm.specification.name",
      "value" : "Java Virtual Machine Specification"
    }, {
      "key" : "user.dir",
      "value" : "/opt/atsd/hbase"
    }, {
      "key" : "user.country",
      "value" : "US"
    }, {
      "key" : "user.language",
      "value" : "en"
    }, {
      "key" : "java.specification.version",
      "value" : "1.6"
    }, {
      "key" : "sun.cpu.endian",
      "value" : "little"
    }, {
      "key" : "java.home",
      "value" : "/usr/lib/jvm/java-6-openjdk-amd64/jre"
    }, {
      "key" : "hbase.log.file",
      "value" : "hbase-axibase-regionserver-NURSWGHBS001.log"
    }, {
      "key" : "sun.jnu.encoding",
      "value" : "ANSI_X3.4-1968"
    }, {
      "key" : "file.separator",
      "value" : "/"
    }, {
      "key" : "java.vendor.url",
      "value" : "http://java.sun.com/"
    }, {
      "key" : "java.awt.graphicsenv",
      "value" : "sun.awt.X11GraphicsEnvironment"
    }, {
      "key" : "os.arch",
      "value" : "amd64"
    }, {
      "key" : "java.io.tmpdir",
      "value" : "/tmp"
    }, {
      "key" : "java.runtime.name",
      "value" : "OpenJDK Runtime Environment"
    }, {
      "key" : "java.awt.printerjob",
      "value" : "sun.print.PSPrinterJob"
    }, {
      "key" : "file.encoding",
      "value" : "ANSI_X3.4-1968"
    }, {
      "key" : "java.version",
      "value" : "1.6.0_35"
    }, {
      "key" : "java.vendor.url.bug",
      "value" : "http://java.sun.com/cgi-bin/bugreport.cgi"
    }, {
      "key" : "java.vm.specification.version",
      "value" : "1.0"
    }, {
      "key" : "file.encoding.pkg",
      "value" : "sun.io"
    }, {
      "key" : "sun.java.command",
      "value" : "org.apache.hadoop.hbase.regionserver.HRegionServer start"
    }, {
      "key" : "sun.java.launcher",
      "value" : "SUN_STANDARD"
    }, {
      "key" : "path.separator",
      "value" : ":"
    }, {
      "key" : "java.runtime.version",
      "value" : "1.6.0_35-b35"
    }, {
      "key" : "java.class.path",
      "value" : "/opt/atsd/hbase/conf:/usr/lib/jvm/java-1.6.0-openjdk-amd64/lib/tools.jar:/opt/atsd/hbase/bin/..:/opt/atsd/hbase/bin/../hbase-0.94.18.jar:/opt/atsd/hbase/bin/../hbase-0.94.18-tests.jar:/opt/atsd/hbase/bin/../lib/activation-1.1.jar:/opt/atsd/hbase/bin/../lib/asm-3.1.jar:/opt/atsd/hbase/bin/../lib/atsd.jar:/opt/atsd/hbase/bin/../lib/avro-1.5.3.jar:/opt/atsd/hbase/bin/../lib/avro-ipc-1.5.3.jar:/opt/atsd/hbase/bin/../lib/commons-beanutils-1.7.0.jar:/opt/atsd/hbase/bin/../lib/commons-beanutils-core-1.8.0.jar:/opt/atsd/hbase/bin/../lib/commons-cli-1.2.jar:/opt/atsd/hbase/bin/../lib/commons-codec-1.4.jar:/opt/atsd/hbase/bin/../lib/commons-collections-3.2.1.jar:/opt/atsd/hbase/bin/../lib/commons-configuration-1.6.jar:/opt/atsd/hbase/bin/../lib/commons-digester-1.8.jar:/opt/atsd/hbase/bin/../lib/commons-el-1.0.jar:/opt/atsd/hbase/bin/../lib/commons-httpclient-3.1.jar:/opt/atsd/hbase/bin/../lib/commons-io-2.1.jar:/opt/atsd/hbase/bin/../lib/commons-lang-2.5.jar:/opt/atsd/hbase/bin/../lib/commons-logging-1.1.1.jar:/opt/atsd/hbase/bin/../lib/commons-math-2.1.jar:/opt/atsd/hbase/bin/../lib/commons-net-1.4.1.jar:/opt/atsd/hbase/bin/../lib/core-3.1.1.jar:/opt/atsd/hbase/bin/../lib/guava-11.0.2.jar:/opt/atsd/hbase/bin/../lib/hadoop-core-1.0.3.jar:/opt/atsd/hbase/bin/../lib/hamcrest-core-1.3.jar:/opt/atsd/hbase/bin/../lib/high-scale-lib-1.1.1.jar:/opt/atsd/hbase/bin/../lib/httpclient-4.1.2.jar:/opt/atsd/hbase/bin/../lib/httpcore-4.1.3.jar:/opt/atsd/hbase/bin/../lib/jackson-core-asl-1.8.8.jar:/opt/atsd/hbase/bin/../lib/jackson-jaxrs-1.8.8.jar:/opt/atsd/hbase/bin/../lib/jackson-mapper-asl-1.8.8.jar:/opt/atsd/hbase/bin/../lib/jackson-xc-1.8.8.jar:/opt/atsd/hbase/bin/../lib/jamon-runtime-2.3.1.jar:/opt/atsd/hbase/bin/../lib/jasper-compiler-5.5.23.jar:/opt/atsd/hbase/bin/../lib/jasper-runtime-5.5.23.jar:/opt/atsd/hbase/bin/../lib/jaxb-api-2.1.jar:/opt/atsd/hbase/bin/../lib/jaxb-impl-2.2.3-1.jar:/opt/atsd/hbase/bin/../lib/jersey-core-1.8.jar:/opt/atsd/hbase/bin/../lib/jersey-json-1.8.jar:/opt/atsd/hbase/bin/../lib/jersey-server-1.8.jar:/opt/atsd/hbase/bin/../lib/jettison-1.1.jar:/opt/atsd/hbase/bin/../lib/jetty-6.1.26.jar:/opt/atsd/hbase/bin/../lib/jetty-util-6.1.26.jar:/opt/atsd/hbase/bin/../lib/jruby-complete-1.6.5.jar:/opt/atsd/hbase/bin/../lib/jsp-2.1-6.1.14.jar:/opt/atsd/hbase/bin/../lib/jsp-api-2.1-6.1.14.jar:/opt/atsd/hbase/bin/../lib/jsr305-1.3.9.jar:/opt/atsd/hbase/bin/../lib/junit-4.11.jar:/opt/atsd/hbase/bin/../lib/libthrift-0.8.0.jar:/opt/atsd/hbase/bin/../lib/log4j-1.2.16.jar:/opt/atsd/hbase/bin/../lib/metrics-core-2.1.2.jar:/opt/atsd/hbase/bin/../lib/netty-3.2.4.Final.jar:/opt/atsd/hbase/bin/../lib/protobuf-java-2.4.0a.jar:/opt/atsd/hbase/bin/../lib/servlet-api-2.5-6.1.14.jar:/opt/atsd/hbase/bin/../lib/slf4j-api-1.4.3.jar:/opt/atsd/hbase/bin/../lib/slf4j-log4j12-1.4.3.jar:/opt/atsd/hbase/bin/../lib/snappy-java-1.0.3.2.jar:/opt/atsd/hbase/bin/../lib/stax-api-1.0.1.jar:/opt/atsd/hbase/bin/../lib/velocity-1.7.jar:/opt/atsd/hbase/bin/../lib/xmlenc-0.52.jar:/opt/atsd/hbase/bin/../lib/zookeeper-3.4.5.jar:"
    }, {
      "key" : "os.name",
      "value" : "Linux"
    }, {
      "key" : "hbase.home.dir",
      "value" : "/opt/atsd/hbase/bin/.."
    }, {
      "key" : "line.separator",
      "value" : "n"
    }, {
      "key" : "os.version",
      "value" : "3.13.0-54-generic"
    }, {
      "key" : "sun.arch.data.model",
      "value" : "64"
    }, {
      "key" : "java.class.version",
      "value" : "50.0"
    }, {
      "key" : "sun.io.unicode.encoding",
      "value" : "UnicodeLittle"
    }, {
      "key" : "java.vendor",
      "value" : "Sun Microsystems Inc."
    }, {
      "key" : "sun.boot.class.path",
      "value" : "/usr/lib/jvm/java-6-openjdk-amd64/jre/lib/resources.jar:/usr/lib/jvm/java-6-openjdk-amd64/jre/lib/rt.jar:/usr/lib/jvm/java-6-openjdk-amd64/jre/lib/sunrsasign.jar:/usr/lib/jvm/java-6-openjdk-amd64/jre/lib/jsse.jar:/usr/lib/jvm/java-6-openjdk-amd64/jre/lib/jce.jar:/usr/lib/jvm/java-6-openjdk-amd64/jre/lib/charsets.jar:/usr/lib/jvm/java-6-openjdk-amd64/jre/lib/jfr.jar:/usr/lib/jvm/java-6-openjdk-amd64/jre/lib/netx.jar:/usr/lib/jvm/java-6-openjdk-amd64/jre/lib/plugin.jar:/usr/lib/jvm/java-6-openjdk-amd64/jre/lib/rhino.jar:/usr/lib/jvm/java-6-openjdk-amd64/jre/classes"
    }, {
      "key" : "hbase.root.logger",
      "value" : "INFO,RFA"
    }, {
      "key" : "java.vm.info",
      "value" : "mixed mode"
    }, {
      "key" : "java.specification.name",
      "value" : "Java Platform API Specification"
    }, {
      "key" : "java.vm.name",
      "value" : "OpenJDK 64-Bit Server VM"
    }, {
      "key" : "java.vm.version",
      "value" : "23.25-b01"
    }, {
      "key" : "sun.boot.library.path",
      "value" : "/usr/lib/jvm/java-6-openjdk-amd64/jre/lib/amd64"
    }, {
      "key" : "java.endorsed.dirs",
      "value" : "/usr/lib/jvm/java-6-openjdk-amd64/jre/lib/endorsed"
    }, {
      "key" : "sun.os.patch.level",
      "value" : "unknown"
    }, {
      "key" : "sun.cpu.isalist",
      "value" : ""
    }, {
      "key" : "hbase.security.logger",
      "value" : "INFO,DRFAS"
    }, {
      "key" : "hbase.id.str",
      "value" : "axibase"
    }, {
      "key" : "user.home",
      "value" : "/home/axibase"
    }, {
      "key" : "java.library.path",
      "value" : "/opt/atsd/hbase/bin/../lib/native/Linux-amd64-64"
    }, {
      "key" : "java.specification.vendor",
      "value" : "Sun Microsystems Inc."
    }, {
      "key" : "sun.management.compiler",
      "value" : "HotSpot 64-Bit Tiered Compilers"
    } ]
  }, {
    "name" : "java.lang:type=ClassLoading",
    "modelerType" : "sun.management.ClassLoadingImpl",
    "LoadedClassCount" : 3504,
    "UnloadedClassCount" : 0,
    "Verbose" : false,
    "TotalLoadedClassCount" : 3504
  }, {
    "name" : "java.lang:type=GarbageCollector,name=ConcurrentMarkSweep",
    "modelerType" : "sun.management.GarbageCollectorImpl",
    "LastGcInfo" : {
      "GcThreadCount" : 14,
      "duration" : 3320,
      "endTime" : 3817667,
      "id" : 38,
      "memoryUsageAfterGc" : [ {
        "key" : "CMS Perm Gen",
        "value" : {
          "committed" : 38866944,
          "init" : 21757952,
          "max" : 174063616,
          "used" : 23302784
        }
      }, {
        "key" : "Code Cache",
        "value" : {
          "committed" : 5636096,
          "init" : 2555904,
          "max" : 50331648,
          "used" : 5475072
        }
      }, {
        "key" : "CMS Old Gen",
        "value" : {
          "committed" : 3457503232,
          "init" : 697499648,
          "max" : 7717519360,
          "used" : 1819514200
        }
      }, {
        "key" : "Par Eden Space",
        "value" : {
          "committed" : 278986752,
          "init" : 278986752,
          "max" : 697958400,
          "used" : 75441800
        }
      }, {
        "key" : "Par Survivor Space",
        "value" : {
          "committed" : 34865152,
          "init" : 34865152,
          "max" : 87228416,
          "used" : 34865152
        }
      } ],
      "memoryUsageBeforeGc" : [ {
        "key" : "CMS Perm Gen",
        "value" : {
          "committed" : 38866944,
          "init" : 21757952,
          "max" : 174063616,
          "used" : 23302784
        }
      }, {
        "key" : "Code Cache",
        "value" : {
          "committed" : 5636096,
          "init" : 2555904,
          "max" : 50331648,
          "used" : 5475072
        }
      }, {
        "key" : "CMS Old Gen",
        "value" : {
          "committed" : 3457503232,
          "init" : 697499648,
          "max" : 7717519360,
          "used" : 3181617712
        }
      }, {
        "key" : "Par Eden Space",
        "value" : {
          "committed" : 278986752,
          "init" : 278986752,
          "max" : 697958400,
          "used" : 1583384
        }
      }, {
        "key" : "Par Survivor Space",
        "value" : {
          "committed" : 34865152,
          "init" : 34865152,
          "max" : 87228416,
          "used" : 29968160
        }
      } ],
      "startTime" : 3814347
    },
    "CollectionCount" : 38,
    "CollectionTime" : 2848,
    "Name" : "ConcurrentMarkSweep",
    "Valid" : true,
    "MemoryPoolNames" : [ "Par Eden Space", "Par Survivor Space", "CMS Old Gen", "CMS Perm Gen" ]
  }, {
    "name" : "java.lang:type=Threading",
    "modelerType" : "sun.management.ThreadImpl",
    "ThreadContentionMonitoringSupported" : true,
    "CurrentThreadCpuTimeSupported" : true,
    "ObjectMonitorUsageSupported" : true,
    "SynchronizerUsageSupported" : true,
    "ThreadContentionMonitoringEnabled" : false,
    "ThreadCpuTimeEnabled" : true,
    "PeakThreadCount" : 89,
    "DaemonThreadCount" : 64,
    "ThreadCount" : 74,
    "TotalStartedThreadCount" : 2833,
    "ThreadCpuTimeSupported" : true,
    "CurrentThreadCpuTime" : 70000000,
    "CurrentThreadUserTime" : 70000000,
    "AllThreadIds" : [ 2841, 2823, 2822, 2759, 2445, 2402, 2003, 110, 91, 87, 85, 82, 81, 77, 73, 72, 71, 70, 69, 68, 67, 66, 65, 64, 63, 62, 61, 60, 59, 58, 57, 56, 55, 54, 53, 52, 51, 50, 49, 9, 22, 39, 38, 37, 36, 42, 48, 47, 46, 44, 40, 35, 34, 33, 30, 29, 28, 27, 25, 23, 20, 19, 18, 17, 16, 15, 14, 13, 12, 11, 10, 5, 3, 2 ]
  }, {
    "name" : "java.util.logging:type=Logging",
    "modelerType" : "java.util.logging.Logging",
    "LoggerNames" : [ "javax.management.snmp", "global", "javax.management.notification", "javax.management.modelmbean", "javax.management.timer", "com.google.common.collect.MapMakerInternalMap", "javax.management", "javax.management.mlet", "javax.management.mbeanserver", "javax.management.snmp.daemon", "javax.management.relation", "javax.management.monitor", "javax.management.misc", "" ]
  }, {
    "name" : "java.lang:type=Compilation",
    "modelerType" : "sun.management.CompilationImpl",
    "Name" : "HotSpot 64-Bit Tiered Compilers",
    "CompilationTimeMonitoringSupported" : true,
    "TotalCompilationTime" : 16024
  }, {
    "name" : "hadoop:service=RegionServer,name=RegionServer",
    "modelerType" : "org.apache.hadoop.hbase.regionserver.MXBeanImpl",
    "ZookeeperQuorum" : "localhost:2181",
    "ServerName" : "NURSWGHBS001,60020,1437465981627",
    "Coprocessors" : [ "BulkDeleteEndpoint", "CompactRawDataEndpoint", "DeleteDataEndpoint" ]
  }, {
    "name" : "java.lang:type=GarbageCollector,name=ParNew",
    "modelerType" : "sun.management.GarbageCollectorImpl",
    "LastGcInfo" : {
      "GcThreadCount" : 14,
      "duration" : 12,
      "endTime" : 3879505,
      "id" : 4161,
      "memoryUsageAfterGc" : [ {
        "key" : "CMS Perm Gen",
        "value" : {
          "committed" : 38866944,
          "init" : 21757952,
          "max" : 174063616,
          "used" : 23876224
        }
      }, {
        "key" : "Code Cache",
        "value" : {
          "committed" : 5636096,
          "init" : 2555904,
          "max" : 50331648,
          "used" : 5516736
        }
      }, {
        "key" : "CMS Old Gen",
        "value" : {
          "committed" : 3457503232,
          "init" : 697499648,
          "max" : 7717519360,
          "used" : 2451682056
        }
      }, {
        "key" : "Par Eden Space",
        "value" : {
          "committed" : 278986752,
          "init" : 278986752,
          "max" : 697958400,
          "used" : 0
        }
      }, {
        "key" : "Par Survivor Space",
        "value" : {
          "committed" : 34865152,
          "init" : 34865152,
          "max" : 87228416,
          "used" : 1127176
        }
      } ],
      "memoryUsageBeforeGc" : [ {
        "key" : "CMS Perm Gen",
        "value" : {
          "committed" : 38866944,
          "init" : 21757952,
          "max" : 174063616,
          "used" : 23876224
        }
      }, {
        "key" : "Code Cache",
        "value" : {
          "committed" : 5636096,
          "init" : 2555904,
          "max" : 50331648,
          "used" : 5516736
        }
      }, {
        "key" : "CMS Old Gen",
        "value" : {
          "committed" : 3457503232,
          "init" : 697499648,
          "max" : 7717519360,
          "used" : 2451682056
        }
      }, {
        "key" : "Par Eden Space",
        "value" : {
          "committed" : 278986752,
          "init" : 278986752,
          "max" : 697958400,
          "used" : 278986752
        }
      }, {
        "key" : "Par Survivor Space",
        "value" : {
          "committed" : 34865152,
          "init" : 34865152,
          "max" : 87228416,
          "used" : 926648
        }
      } ],
      "startTime" : 3879493
    },
    "CollectionCount" : 4161,
    "CollectionTime" : 98027,
    "Name" : "ParNew",
    "Valid" : true,
    "MemoryPoolNames" : [ "Par Eden Space", "Par Survivor Space" ]
  }, {
    "name" : "hadoop:service=RegionServer,name=RegionServerDynamicStatistics",
    "modelerType" : "org.apache.hadoop.hbase.regionserver.metrics.RegionServerDynamicStatistics",
    "tbl.atsd_tag.cf.v.n.blockCacheSize" : 5032,
    "tbl.atsd_metric.cf.t.staticIndexSizeKB" : 0,
    "tbl.atsd_d.region.c167a8fcd28c9afb85c91680ae17f749.writerequestcount" : 117183,
    "tbl.atsd_d.region.3e3c21ca8e370eaeba45cc4da0af2a95.readrequestcount" : 0,
    "tbl.atsd_entity.cf.i.storeFileCount" : 2,
    "storeFileCount" : 151,
    "tbl.atsd_forecast_settings.cf.f.storeFileCount" : 0,
    "tbl..META..cf.info.fsBlockReadCacheHitCnt" : 0,
    "tbl.atsd_export_job.cf.c.storeFileSizeMB" : 0,
    "tbl.atsd_rule_threshold.cf.c.staticIndexSizeKB" : 0,
    "tbl.atsd_message_source.cf.n.staticBloomSizeKB" : 0,
    "tbl.atsd_sql.cf.d.storeFileSizeMB" : 0,
    "tbl.atsd_counter.cf.type.storeFileCount" : 1,
    "tbl.atsd_d.region.4652ccca328783c00aef7744d8198a45.readrequestcount" : 0,
    "bt.Data.compactionBlockReadCacheMissCnt" : 3820,
    "tbl.atsd_rule_alert.cf.r.storeFileIndexSizeMB" : 0,
    "tbl.atsd_d.region.5db3327abd3ace37e60b02c4c8ea34fa.writerequestcount" : 91805,
    "tbl.-ROOT-.cf.info.blockCacheSize" : 2304,
    "tbl.atsd_d.region.72f0735f757706f0f64ebd07205b6e68.writerequestcount" : 91800,
    "tbl.atsd_tag.cf.v.i.flushSize" : 400,
    "tbl.atsd_d.cf.r.multiput_NumOps" : 2,
    "tbl.atsd_d.cf.r.multiput_AvgTime" : 0,
    "tbl.atsd_d.cf.r.multiput_MinTime" : 0,
    "tbl.atsd_d.cf.r.multiput_MaxTime" : 5,
    "tbl.atsd_nmon_uarg_data.cf.c.staticIndexSizeKB" : 0,
    "tbl.atsd_option.cf.o.storeFileSizeMB" : 0,
    "tbl.atsd_message_source.cf.i.storeFileSizeMB" : 0,
    "tbl.atsd_rule.cf.f.storeFileSizeMB" : 0,
    "tbl.atsd_portal_config.cf.c.storeFileCount" : 3,
    "tbl.atsd_failure.cf.c.storeFileCount" : 0,
    "bt.Index.fsBlockReadCacheHitCnt" : 0,
    "tbl.atsd_d.region.b15a18803f07d7280529caea5d44ee9d.readrequestcount" : 0,
    "bt.Index.compactionBlockReadCnt" : 1,
    "tbl.atsd_message_source.cf.n.staticIndexSizeKB" : 0,
    "tbl.atsd_forecast.cf.f.staticIndexSizeKB" : 0,
    "compactionBlockReadCacheMissCnt" : 3821,
    "blockCacheSize" : 3092192,
    "tbl.atsd_d.cf.r.fsBlockReadCnt" : 0,
    "tbl.atsd_message.cf.m.storeFileSizeMB" : 0,
    "tbl.atsd_tag.cf.k.n.storeFileCount" : 2,
    "tbl.atsd_message_type.cf.i.storeFileSizeMB" : 0,
    "tbl.atsd_message_source.cf.n.storeFileIndexSizeMB" : 0,
    "tbl.atsd_tag.cf.k.n.storeFileSizeMB" : 0,
    "tbl.atsd_entity_lookup.cf.c.staticIndexSizeKB" : 0,
    "tbl.atsd_tag.cf.k.n.staticBloomSizeKB" : 0,
    "tbl.atsd_message_source.cf.i.staticIndexSizeKB" : 0,
    "tbl.atsd_d.region.13f28d976f5a30d7420bec9a16b0d492.multiput_NumOps" : 0,
    "tbl.atsd_d.region.13f28d976f5a30d7420bec9a16b0d492.multiput_AvgTime" : 0,
    "tbl.atsd_d.region.13f28d976f5a30d7420bec9a16b0d492.multiput_MinTime" : 1,
    "tbl.atsd_d.region.13f28d976f5a30d7420bec9a16b0d492.multiput_MaxTime" : 2,
    "tbl.atsd_d.region.c167a8fcd28c9afb85c91680ae17f749.readrequestcount" : 0,
    "tbl.atsd_rule_alert.cf.r.storeFileSizeMB" : 0,
    "tbl.atsd_option.cf.o.blockCacheSize" : 720,
    "tbl.atsd_forecast.cf.m.staticBloomSizeKB" : 0,
    "tbl.atsd_entity.cf.i.memstoreSizeMB" : 0,
    "tbl.atsd_entity.cf.i.staticBloomSizeKB" : 0,
    "memstoreSizeMB.max" : 573,
    "tbl.atsd_forecast.cf.m.storeFileSizeMB" : 0,
    "tbl.atsd_delete_task.cf.t.storeFileIndexSizeMB" : 0,
    "tbl.atsd_forecast_settings.cf.f.storeFileSizeMB" : 0,
    "tbl.atsd_entity_group.cf.e.staticBloomSizeKB" : 0,
    "tbl.atsd_message.cf.e.storeFileCount" : 0,
    "tbl.atsd_d.cf.r.bt.Index.fsBlockReadCnt" : 0,
    "tbl.atsd_calendar.cf.c.storeFileIndexSizeMB" : 0,
    "tbl.atsd_metric.cf.n.staticIndexSizeKB" : 0,
    "tbl.atsd_join.cf.c.staticIndexSizeKB" : 0,
    "tbl.atsd_rule.cf.r.storeFileSizeMB" : 0,
    "tbl.atsd_message.cf.t.storeFileIndexSizeMB" : 0,
    "tbl.atsd_rule_threshold.cf.c.staticBloomSizeKB" : 0,
    "tbl.atsd_portal_config.cf.c.bt.Data.blockCacheSize" : 372888,
    "tbl..META..cf.info.memstoreSizeMB" : 0,
    "tbl.atsd_message_source.cf.n.storeFileCount" : 0,
    "tbl.atsd_counter.cf.type.memstoreSizeMB" : 0,
    "tbl.-ROOT-.cf.info.storeFileIndexSizeMB" : 0,
    "tbl.atsd_tag.cf.k.i.staticBloomSizeKB" : 0,
    "tbl.atsd_d.region.b15a18803f07d7280529caea5d44ee9d.multiput_NumOps" : 0,
    "tbl.atsd_d.region.b15a18803f07d7280529caea5d44ee9d.multiput_AvgTime" : 0,
    "tbl.atsd_d.region.b15a18803f07d7280529caea5d44ee9d.multiput_MinTime" : 2,
    "tbl.atsd_d.region.b15a18803f07d7280529caea5d44ee9d.multiput_MaxTime" : 3,
    "tbl.atsd_rule.cf.r.staticIndexSizeKB" : 0,
    "tbl.atsd_nmon_df_data.cf.c.storeFileIndexSizeMB" : 0,
    "tbl.atsd_message_source.cf.n.storeFileSizeMB" : 0,
    "tbl.atsd_forecast.cf.f.staticBloomSizeKB" : 0,
    "tbl.atsd_counter.cf.type.storeFileSizeMB" : 0,
    "tbl.atsd_entity_group.cf.g.bt.Data.blockCacheSize" : 7792,
    "tbl.atsd_d.region.1bc65979589989b6a6548b0282b46630.multiput_NumOps" : 0,
    "tbl.atsd_d.region.1bc65979589989b6a6548b0282b46630.multiput_AvgTime" : 0,
    "tbl.atsd_d.region.1bc65979589989b6a6548b0282b46630.multiput_MinTime" : 3,
    "tbl.atsd_d.region.1bc65979589989b6a6548b0282b46630.multiput_MaxTime" : 18,
    "tbl.atsd_d.region.ff52589081aba06799b31f495433e25c.multiput_NumOps" : 0,
    "tbl.atsd_d.region.ff52589081aba06799b31f495433e25c.multiput_AvgTime" : 0,
    "tbl.atsd_d.region.ff52589081aba06799b31f495433e25c.multiput_MinTime" : 1,
    "tbl.atsd_d.region.ff52589081aba06799b31f495433e25c.multiput_MaxTime" : 19,
    "tbl.atsd_d.region.7d449171565c8c33eee07f64e77cce2b.writerequestcount" : 214396,
    "responseQueuesSize" : 0,
    "tbl.atsd_entity.cf.t.storeFileCount" : 0,
    "tbl.atsd_sql.cf.d.storeFileCount" : 0,
    "tbl.atsd_counter.region.633ea1f376a03819eb4b73e5bfbd9749.writerequestcount" : 16,
    "tbl.atsd_message.cf.e.staticBloomSizeKB" : 0,
    "tbl.atsd_entity_lookup.cf.c.memstoreSizeMB" : 0,
    "tbl.atsd_d.region.52ae70a00c3d4c78e8413c788e14fff1.writerequestcount" : 213556,
    "tbl.testtable.cf.colfam.storeFileIndexSizeMB" : 0,
    "tbl.atsd_option.cf.o.bt.Data.blockCacheSize" : 720,
    "tbl.atsd_sql.cf.t.storeFileIndexSizeMB" : 0,
    "tbl.atsd_join.cf.c.storeFileSizeMB" : 0,
    "tbl.atsd_tag.cf.v.n.staticIndexSizeKB" : 0,
    "tbl.atsd_nmon.cf.c.memstoreSizeMB" : 0,
    "tbl.atsd_entity.cf.n.bt.Data.blockCacheSize" : 7000,
    "tbl..META..cf.info.bt.Data.fsBlockReadCnt" : 0,
    "tbl.atsd_d.cf.r.bt.Index.blockCacheSize" : 658128,
    "fsBlockReadCacheHitCnt" : 0,
    "tbl.testtable.cf.colfam.storeFileCount" : 0,
    "tbl.atsd_entity.cf.n.staticBloomSizeKB" : 0,
    "tbl.atsd_message.cf.m.storeFileCount" : 0,
    "tbl.atsd_d.cf.r.storeFileIndexSizeMB" : 0,
    "tbl.atsd_rule_threshold.cf.c.memstoreSizeMB" : 0,
    "tbl.atsd_entity.cf.i.staticIndexSizeKB" : 0,
    "tbl.atsd_rule_alert.cf.r.memstoreSizeMB" : 0,
    "tbl.atsd_rule_threshold.cf.c.storeFileSizeMB" : 0,
    "tbl.atsd_user.cf.c.staticIndexSizeKB" : 0,
    "tbl.atsd_entity.cf.t.storeFileIndexSizeMB" : 0,
    "tbl.atsd_properties.cf.c.staticIndexSizeKB" : 0,
    "tbl.atsd_entity.cf.t.staticIndexSizeKB" : 0,
    "tbl.atsd_message.cf.t.staticBloomSizeKB" : 0,
    "tbl.atsd_message_source.cf.i.storeFileIndexSizeMB" : 0,
    "tbl.atsd_csv.cf.c.storeFileIndexSizeMB" : 0,
    "tbl.atsd_message.cf.e.memstoreSizeMB" : 0,
    "tbl.atsd_failure.cf.c.staticBloomSizeKB" : 0,
    "tbl.atsd_d.cf.r.staticIndexSizeKB" : 139588,
    "tbl.atsd_metric.cf.i.storeFileIndexSizeMB" : 0,
    "tbl.atsd_message_source.cf.n.memstoreSizeMB" : 0,
    "tbl.atsd_entity.cf.i.storeFileIndexSizeMB" : 0,
    "tbl.atsd_calendar.cf.c.storeFileSizeMB" : 0,
    "tbl.atsd_tag.cf.k.n.memstoreSizeMB" : 0,
    "tbl.atsd_tag.cf.k.i.memstoreSizeMB" : 0,
    "tbl.atsd_forecast.cf.f.memstoreSizeMB" : 0,
    "tbl.-ROOT-.cf.info.staticIndexSizeKB" : 0,
    "tbl.atsd_d.region.6bc425124a32383cf8ca9a1e70fbaf96.writerequestcount" : 61140,
    "tbl.atsd_sql.cf.t.storeFileSizeMB" : 0,
    "tbl..META..cf.info.staticIndexSizeKB" : 0,
    "tbl.atsd_properties.cf.c.storeFileSizeMB" : 0,
    "tbl.atsd_nmon_uarg_data.cf.c.memstoreSizeMB" : 0,
    "tbl.atsd_d.region.4652ccca328783c00aef7744d8198a45.writerequestcount" : 69863,
    "tbl.atsd_properties.cf.c.storeFileCount" : 2,
    "tbl.atsd_entity.cf.n.storeFileIndexSizeMB" : 0,
    "tbl.atsd_d.region.870290b5875455e821a1e87c964e9dd7.writerequestcount" : 214428,
    "tbl.atsd_entity.cf.n.staticIndexSizeKB" : 0,
    "tbl.atsd_d.cf.r.fsBlockReadCacheHitCnt" : 0,
    "tbl.atsd_d.region.554c56a183bfec1037fd06c49123d084.readrequestcount" : 0,
    "bt.Index.compactionReadNumOps" : 1,
    "bt.Index.compactionReadAvgTime" : 594273,
    "bt.Index.compactionReadMinTime" : 266233,
    "bt.Index.compactionReadMaxTime" : 709721,
    "tbl.atsd_nmon_df_data.cf.c.staticIndexSizeKB" : 0,
    "tbl.atsd_sql.cf.d.memstoreSizeMB" : 0,
    "tbl.atsd_d.cf.r.compactionBlockReadCacheMissCnt" : 3821,
    "tbl.atsd_nmon.cf.c.staticIndexSizeKB" : 0,
    "tbl.atsd_d.cf.r.bt.Data.fsBlockReadCnt" : 0,
    "tbl.atsd_counter.cf.type.storeFileIndexSizeMB" : 0,
    "tbl.atsd_forecast.cf.m.staticIndexSizeKB" : 0,
    "tbl.atsd_collection.cf.c.memstoreSizeMB" : 0,
    "tbl.atsd_portal_config.cf.c.storeFileIndexSizeMB" : 0,
    "tbl.atsd_rule.cf.r.storeFileIndexSizeMB" : 0,
    "tbl.atsd_message.cf.e.staticIndexSizeKB" : 0,
    "tbl.atsd_properties.cf.c.staticBloomSizeKB" : 0,
    "tbl.atsd_rule_alert.cf.r.staticIndexSizeKB" : 0,
    "tbl.atsd_option.cf.o.staticIndexSizeKB" : 0,
    "tbl.atsd_calendar.cf.c.storeFileCount" : 0,
    "tbl.atsd_d.region.650576fd33d93c61f49f6cd2e7e861bd.multiput_NumOps" : 0,
    "tbl.atsd_d.region.650576fd33d93c61f49f6cd2e7e861bd.multiput_AvgTime" : 0,
    "tbl.atsd_d.region.650576fd33d93c61f49f6cd2e7e861bd.multiput_MinTime" : 2,
    "tbl.atsd_d.region.650576fd33d93c61f49f6cd2e7e861bd.multiput_MaxTime" : 3,
    "tbl.atsd_message_type.cf.i.storeFileIndexSizeMB" : 0,
    "tbl.atsd_collection.cf.c.storeFileCount" : 0,
    "tbl.atsd_metric.cf.i.storeFileSizeMB" : 0,
    "tbl.atsd_tag.region.d12235deec49144e3b0e3555251e56e2.writerequestcount" : 4,
    "tbl.atsd_message_type.cf.n.storeFileIndexSizeMB" : 0,
    "tbl.atsd_tag.cf.v.n.memstoreSizeMB" : 0,
    "tbl.atsd_user.cf.c.storeFileSizeMB" : 0,
    "tbl.atsd_tag.cf.v.i.staticIndexSizeKB" : 0,
    "tbl.atsd_nmon.cf.c.storeFileIndexSizeMB" : 0,
    "tbl.testtable.cf.colfam.memstoreSizeMB" : 0,
    "tbl.atsd_d.region.d7cb15a8efe990a9be13d7786eb1e3ae.writerequestcount" : 91786,
    "tbl.atsd_entity.cf.t.memstoreSizeMB" : 0,
    "tbl.atsd_d.region.8370f69e2a9782adf919b8e551f715a3.writerequestcount" : 61131,
    "tbl.atsd_message_source.cf.i.storeFileCount" : 0,
    "tbl.atsd_d.cf.r.bt.Index.compactionBlockReadCacheMissCnt" : 1,
    "tbl.atsd_metric.cf.t.memstoreSizeMB" : 0,
    "tbl.atsd_message_type.cf.n.staticBloomSizeKB" : 0,
    "tbl.atsd_message_type.cf.i.memstoreSizeMB" : 0,
    "tbl.atsd_csv.cf.c.memstoreSizeMB" : 0,
    "tbl.atsd_tag.cf.v.i.staticBloomSizeKB" : 0,
    "tbl.atsd_entity_group.cf.g.nextsize" : 3333,
    "tbl.atsd_collection.cf.c.storeFileSizeMB" : 0,
    "tbl.atsd_join.cf.c.storeFileCount" : 0,
    "tbl.atsd_failure.cf.c.memstoreSizeMB" : 0,
    "tbl.atsd_entity_group.cf.e.staticIndexSizeKB" : 0,
    "tbl.atsd_metric.cf.n.storeFileSizeMB" : 0,
    "tbl.atsd_tag.cf.v.n.storeFileIndexSizeMB" : 0,
    "tbl.atsd_collection.cf.c.storeFileIndexSizeMB" : 0,
    "bt.Index.fsBlockReadCnt" : 0,
    "tbl.atsd_counter.region.633ea1f376a03819eb4b73e5bfbd9749.readrequestcount" : 8,
    "tbl.atsd_message.cf.t.storeFileSizeMB" : 0,
    "tbl.atsd_message_type.cf.i.storeFileCount" : 0,
    "tbl.atsd_tag.cf.v.n.bt.Data.blockCacheSize" : 5032,
    "tbl.atsd_message.cf.t.staticIndexSizeKB" : 0,
    "tbl.atsd_notification.cf.c.memstoreSizeMB" : 0,
    "tbl.-ROOT-.cf.info.storeFileCount" : 3,
    "tbl.atsd_metric.cf.n.memstoreSizeMB" : 0,
    "staticBloomSizeKB" : 0,
    "tbl.atsd_d.region.648750c4b983eddd0ee24fd3f8ac9d7f.writerequestcount" : 91786,
    "tbl.atsd_user.cf.c.staticBloomSizeKB" : 0,
    "tbl.atsd_d.region.33d2571ea0dd388fbd7b43cd53b063eb.writerequestcount" : 91796,
    "tbl.atsd_entity.cf.n.blockCacheSize" : 7000,
    "tbl..META..cf.info.bt.Data.blockCacheSize" : 66312,
    "tbl.atsd_csv.cf.c.storeFileSizeMB" : 0,
    "tbl.atsd_portal_config.cf.c.staticBloomSizeKB" : 0,
    "tbl.atsd_message_source.cf.i.staticBloomSizeKB" : 0,
    "tbl.atsd_portal_config.region.f31953aa0d8924606941d87f0dc0d18f.readrequestcount" : 2,
    "tbl.atsd_message_type.cf.n.memstoreSizeMB" : 0,
    "bt.Data.compactionBlockReadCnt" : 3820,
    "tbl.atsd_forecast_settings.cf.f.storeFileIndexSizeMB" : 0,
    "tbl.atsd_metric.cf.i.storeFileCount" : 1,
    "tbl.atsd_option.cf.o.staticBloomSizeKB" : 0,
    "tbl.atsd_message.cf.m.staticIndexSizeKB" : 0,
    "tbl.atsd_d.region.ff52589081aba06799b31f495433e25c.readrequestcount" : 0,
    "tbl..META..cf.info.multiput_NumOps" : 0,
    "tbl..META..cf.info.multiput_AvgTime" : 0,
    "tbl..META..cf.info.multiput_MinTime" : 1,
    "tbl..META..cf.info.multiput_MaxTime" : 1,
    "tbl.atsd_d.region.48538dbf52c3a8d94ba1589b64ed9997.writerequestcount" : 61142,
    "tbl.atsd_sql.cf.d.storeFileIndexSizeMB" : 0,
    "tbl.atsd_nmon_df_data.cf.c.storeFileSizeMB" : 0,
    "tbl.atsd_entity.cf.i.bt.Data.blockCacheSize" : 2608,
    "tbl.atsd_entity_group.cf.g.staticIndexSizeKB" : 0,
    "tbl..META..cf.info.bt.Data.fsBlockReadCacheHitCnt" : 0,
    "tbl.atsd_metric.cf.n.storeFileCount" : 1,
    "tbl.atsd_d.region.f10eb376ecfe39675ebd3e85c1d15652.readrequestcount" : 0,
    "tbl.atsd_rule_alert.cf.r.staticBloomSizeKB" : 0,
    "tbl.atsd_user.cf.c.storeFileIndexSizeMB" : 0,
    "tbl.atsd_metric.cf.i.staticBloomSizeKB" : 0,
    "tbl.-ROOT-.region.70236052.writerequestcount" : 1,
    "tbl.atsd_metric.cf.i.bt.Data.blockCacheSize" : 5816,
    "tbl.atsd_entity_group.cf.e.storeFileSizeMB" : 0,
    "tbl.atsd_d.cf.r.compactionBlockReadCacheHitCnt" : 0,
    "tbl.atsd_d.region.b15a18803f07d7280529caea5d44ee9d.writerequestcount" : 83368,
    "tbl..META..cf.info.storeFileIndexSizeMB" : 0,
    "tbl.atsd_delete_task.cf.t.memstoreSizeMB" : 0,
    "tbl.atsd_d.region.ff52589081aba06799b31f495433e25c.writerequestcount" : 107730,
    "tbl..META..region.1028785192.multiput_NumOps" : 0,
    "tbl..META..region.1028785192.multiput_AvgTime" : 0,
    "tbl..META..region.1028785192.multiput_MinTime" : 1,
    "tbl..META..region.1028785192.multiput_MaxTime" : 1,
    "tbl.atsd_d.cf.r.bt.Data.compactionBlockReadCnt" : 3820,
    "tbl.atsd_entity.cf.n.memstoreSizeMB" : 0,
    "tbl..META..cf.info.getsize" : 0,
    "tbl.atsd_d.region.c167a8fcd28c9afb85c91680ae17f749.multiput_NumOps" : 0,
    "tbl.atsd_d.region.c167a8fcd28c9afb85c91680ae17f749.multiput_AvgTime" : 0,
    "tbl.atsd_d.region.c167a8fcd28c9afb85c91680ae17f749.multiput_MinTime" : 1,
    "tbl.atsd_d.region.c167a8fcd28c9afb85c91680ae17f749.multiput_MaxTime" : 3,
    "tbl..META..cf.info.get_NumOps" : 0,
    "tbl..META..cf.info.get_AvgTime" : 0,
    "tbl..META..cf.info.get_MinTime" : 0,
    "tbl..META..cf.info.get_MaxTime" : 0,
    "tbl.atsd_csv.cf.c.storeFileCount" : 0,
    "tbl..META..cf.info.staticBloomSizeKB" : 0,
    "tbl.atsd_d.region.e163e4d40b9837d5b4140655490e78b2.writerequestcount" : 91792,
    "tbl.atsd_entity_group.cf.g.memstoreSizeMB" : 0,
    "tbl.atsd_tag.cf.v.n.flushSize" : 392,
    "tbl.atsd_d.cf.r.bt.Index.fsBlockReadCacheHitCnt" : 0,
    "tbl.atsd_entity.cf.i.storeFileSizeMB" : 0,
    "tbl.atsd_d.cf.r.flushSize" : 67847270768,
    "tbl.atsd_message.cf.t.memstoreSizeMB" : 0,
    "tbl.atsd_nmon_df_data.cf.c.staticBloomSizeKB" : 0,
    "tbl.-ROOT-.cf.info.staticBloomSizeKB" : 0,
    "tbl.atsd_d.region.7a52daba613c8c63ab275a75ef32a6ae.writerequestcount" : 91797,
    "tbl.atsd_entity_group.cf.g.storeFileSizeMB" : 0,
    "tbl.atsd_d.cf.r.bt.Data.blockCacheSize" : 1958032,
    "tbl.atsd_notification.cf.c.storeFileCount" : 0,
    "tbl.atsd_join.cf.c.memstoreSizeMB" : 0,
    "tbl.atsd_counter.cf.type.staticIndexSizeKB" : 0,
    "tbl.atsd_message.cf.c.staticBloomSizeKB" : 0,
    "tbl.atsd_message.cf.c.storeFileSizeMB" : 0,
    "tbl.atsd_d.cf.r.compactionReadNumOps" : 3821,
    "tbl.atsd_d.cf.r.compactionReadAvgTime" : 837453,
    "tbl.atsd_d.cf.r.compactionReadMinTime" : 432502,
    "tbl.atsd_d.cf.r.compactionReadMaxTime" : 5291453,
    "tbl.atsd_entity.cf.n.flushSize" : 800,
    "tbl.atsd_rule.cf.f.memstoreSizeMB" : 0,
    "tbl.atsd_entity_group.cf.g.storeFileIndexSizeMB" : 0,
    "tbl.-ROOT-.cf.info.bt.Data.blockCacheSize" : 2304,
    "tbl.atsd_d.region.74ed25bfcf985437a8fbf967ec6ff19b.writerequestcount" : 61171,
    "tbl.atsd_nmon_df_data.cf.c.storeFileCount" : 0,
    "tbl.atsd_properties.cf.c.memstoreSizeMB" : 0,
    "tbl.atsd_d.region.cf78a14af314548fdccf5454f5353089.readrequestcount" : 3056,
    "bt.Data.compactionReadNumOps" : 3820,
    "bt.Data.compactionReadAvgTime" : 837517,
    "bt.Data.compactionReadMinTime" : 432555,
    "bt.Data.compactionReadMaxTime" : 5291453,
    "tbl.atsd_export_job.cf.c.storeFileCount" : 0,
    "tbl.atsd_rule_threshold.cf.c.storeFileCount" : 0,
    "tbl.atsd_message_type.cf.n.storeFileSizeMB" : 0,
    "tbl.atsd_d.cf.r.memstoreSizeMB" : 2585,
    "tbl.atsd_d.region.650576fd33d93c61f49f6cd2e7e861bd.writerequestcount" : 116305,
    "tbl.atsd_metric.cf.i.blockCacheSize" : 5816,
    "tbl.atsd_rule.cf.f.staticIndexSizeKB" : 0,
    "tbl.atsd_metric.region.296a067b5b1833809c566a2784d073ea.readrequestcount" : 13,
    "tbl.atsd_message.cf.t.storeFileCount" : 0,
    "tbl.testtable.cf.colfam.staticIndexSizeKB" : 0,
    "bt.Data.fsBlockReadCacheHitCnt" : 0,
    "tbl.atsd_entity_group.cf.e.storeFileCount" : 0,
    "staticIndexSizeKB" : 139588,
    "tbl.atsd_d.cf.r.bt.Index.compactionBlockReadCacheHitCnt" : 0,
    "tbl.atsd_entity.cf.n.storeFileCount" : 2,
    "tbl.atsd_message.cf.m.storeFileIndexSizeMB" : 0,
    "tbl.atsd_entity.cf.n.storeFileSizeMB" : 0,
    "tbl.atsd_rule.cf.r.memstoreSizeMB" : 0,
    "tbl.atsd_metric.cf.n.blockCacheSize" : 5560,
    "tbl.atsd_sql.cf.t.staticBloomSizeKB" : 0,
    "tbl.atsd_entity.region.17e094625d4e79d40c2945336d52459e.writerequestcount" : 11,
    "tbl.testtable.cf.colfam.storeFileSizeMB" : 0,
    "tbl.atsd_d.region.554c56a183bfec1037fd06c49123d084.writerequestcount" : 98003,
    "tbl.atsd_message.cf.m.staticBloomSizeKB" : 0,
    "tbl.atsd_d.region.3f3a81a06ef874b53be26a88f8fda4f3.writerequestcount" : 91794,
    "storeFileSizeMB" : 229421,
    "bt.Index.compactionBlockReadCacheMissCnt" : 1,
    "tbl.atsd_entity.cf.i.flushSize" : 800,
    "tbl.atsd_metric.cf.t.storeFileCount" : 0,
    "tbl.atsd_entity_group.cf.g.staticBloomSizeKB" : 0,
    "tbl.atsd_tag.cf.v.n.storeFileCount" : 2,
    "tbl.atsd_d.region.870290b5875455e821a1e87c964e9dd7.multiput_NumOps" : 0,
    "tbl.atsd_d.region.870290b5875455e821a1e87c964e9dd7.multiput_AvgTime" : 0,
    "tbl.atsd_d.region.870290b5875455e821a1e87c964e9dd7.multiput_MinTime" : 1,
    "tbl.atsd_d.region.870290b5875455e821a1e87c964e9dd7.multiput_MaxTime" : 10,
    "tbl..META..cf.info.fsBlockReadCnt" : 0,
    "tbl.atsd_export_job.cf.c.staticIndexSizeKB" : 0,
    "tbl.atsd_message.cf.c.memstoreSizeMB" : 0,
    "tbl.atsd_metric.cf.n.staticBloomSizeKB" : 0,
    "tbl.atsd_tag.cf.k.i.storeFileIndexSizeMB" : 0,
    "staticBloomSizeKB.max" : 0,
    "tbl.atsd_metric.cf.t.storeFileSizeMB" : 0,
    "tbl.atsd_d.region.ad903df8e36378da5926ee080ab4dcca.multiput_NumOps" : 0,
    "tbl.atsd_d.region.ad903df8e36378da5926ee080ab4dcca.multiput_AvgTime" : 0,
    "tbl.atsd_d.region.ad903df8e36378da5926ee080ab4dcca.multiput_MinTime" : 1,
    "tbl.atsd_d.region.ad903df8e36378da5926ee080ab4dcca.multiput_MaxTime" : 4,
    "tbl.atsd_d.region.650576fd33d93c61f49f6cd2e7e861bd.readrequestcount" : 0,
    "tbl.atsd_entity_group.cf.g.blockCacheSize" : 7792,
    "tbl.atsd_message_type.cf.i.staticIndexSizeKB" : 0,
    "tbl.atsd_sql.cf.t.memstoreSizeMB" : 0,
    "tbl.atsd_entity_group.cf.e.storeFileIndexSizeMB" : 0,
    "tbl.atsd_rule.cf.r.staticBloomSizeKB" : 0,
    "tbl.atsd_csv.cf.c.staticBloomSizeKB" : 0,
    "tbl.atsd_nmon.cf.c.storeFileCount" : 1,
    "tbl.atsd_calendar.cf.c.memstoreSizeMB" : 0,
    "tbl.atsd_entity.cf.i.blockCacheSize" : 2608,
    "tbl.atsd_forecast.cf.f.storeFileIndexSizeMB" : 0,
    "tbl.atsd_tag.cf.v.i.storeFileIndexSizeMB" : 0,
    "tbl.atsd_tag.cf.v.n.storeFileSizeMB" : 0,
    "tbl.atsd_rule.cf.r.storeFileCount" : 0,
    "tbl.atsd_tag.cf.k.n.storeFileIndexSizeMB" : 0,
    "tbl.-ROOT-.cf.info.flushSize" : 376,
    "bt.Data.fsBlockReadCnt" : 0,
    "tbl.atsd_delete_task.cf.t.storeFileCount" : 0,
    "tbl.atsd_d.region.ad903df8e36378da5926ee080ab4dcca.writerequestcount" : 214408,
    "tbl.atsd_entity.cf.t.staticBloomSizeKB" : 0,
    "tbl.atsd_option.cf.o.storeFileCount" : 1,
    "tbl.atsd_join.cf.c.storeFileIndexSizeMB" : 0,
    "tbl.atsd_portal_config.cf.c.memstoreSizeMB" : 0,
    "tbl.atsd_delete_task.cf.t.staticBloomSizeKB" : 0,
    "tbl.atsd_notification.cf.c.storeFileSizeMB" : 0,
    "tbl.atsd_d.cf.r.bt.Data.fsBlockReadCacheHitCnt" : 0,
    "tbl.atsd_metric.cf.n.storeFileIndexSizeMB" : 0,
    "tbl.atsd_entity.cf.n.nextsize" : 5180,
    "compactionReadNumOps" : 3821,
    "compactionReadAvgTime" : 837453,
    "compactionReadMinTime" : 432502,
    "compactionReadMaxTime" : 5291453,
    "tbl.atsd_message_type.cf.n.staticIndexSizeKB" : 0,
    "tbl.atsd_d.region.96ae99a202701ba505074c1f60ce01fd.writerequestcount" : 61152,
    "bt.Data.blockCacheSize" : 2434064,
    "tbl.atsd_tag.cf.v.i.storeFileCount" : 2,
    "tbl.atsd_forecast.cf.f.storeFileSizeMB" : 0,
    "tbl.atsd_d.cf.r.storeFileCount" : 120,
    "tbl.atsd_forecast.cf.m.storeFileIndexSizeMB" : 0,
    "tbl.atsd_rule.cf.f.storeFileIndexSizeMB" : 0,
    "tbl.atsd_collection.cf.c.staticIndexSizeKB" : 0,
    "tbl.atsd_message_source.cf.i.memstoreSizeMB" : 0,
    "tbl.atsd_tag.cf.k.i.storeFileSizeMB" : 0,
    "tbl.-ROOT-.cf.info.memstoreSizeMB" : 0,
    "tbl.atsd_message_type.cf.i.staticBloomSizeKB" : 0,
    "tbl.atsd_sql.cf.d.staticBloomSizeKB" : 0,
    "tbl.atsd_tag.cf.v.i.memstoreSizeMB" : 0,
    "tbl.atsd_entity_lookup.cf.c.storeFileSizeMB" : 0,
    "tbl.atsd_properties.region.f51f4f43aa3fd1c681ab696e3ab7cf63.readrequestcount" : 0,
    "tbl..META..cf.info.storeFileCount" : 3,
    "tbl.atsd_sql.cf.d.staticIndexSizeKB" : 0,
    "tbl..META..region.1028785192.writerequestcount" : 74,
    "tbl.atsd_d.cf.r.storeFileSizeMB" : 229421,
    "tbl.atsd_d.cf.r.bt.Data.compactionReadNumOps" : 3820,
    "tbl.atsd_d.cf.r.bt.Data.compactionReadAvgTime" : 837517,
    "tbl.atsd_d.cf.r.bt.Data.compactionReadMinTime" : 432555,
    "tbl.atsd_d.cf.r.bt.Data.compactionReadMaxTime" : 5291453,
    "tbl.atsd_calendar.cf.c.staticIndexSizeKB" : 0,
    "tbl.atsd_delete_task.cf.t.staticIndexSizeKB" : 0,
    "tbl.atsd_entity_group.cf.g.storeFileCount" : 2,
    "tbl.atsd_d.region.13f28d976f5a30d7420bec9a16b0d492.writerequestcount" : 214408,
    "tbl.atsd_export_job.cf.c.staticBloomSizeKB" : 0,
    "tbl.atsd_export_job.cf.c.memstoreSizeMB" : 0,
    "tbl..META..cf.info.storeFileSizeMB" : 0,
    "tbl.atsd_notification.cf.c.staticBloomSizeKB" : 0,
    "tbl.atsd_tag.cf.k.i.storeFileCount" : 2,
    "tbl.atsd_entity_group.cf.e.memstoreSizeMB" : 0,
    "tbl.atsd_entity.region.17e094625d4e79d40c2945336d52459e.readrequestcount" : 4440,
    "tbl.atsd_tag.region.d12235deec49144e3b0e3555251e56e2.readrequestcount" : 6,
    "tbl.atsd_option.cf.o.storeFileIndexSizeMB" : 0,
    "tbl.atsd_properties.cf.c.storeFileIndexSizeMB" : 0,
    "tbl.atsd_rule.cf.f.storeFileCount" : 0,
    "tbl.atsd_option.region.01542c703b1a7e1c54fbad1a7782d698.readrequestcount" : 3,
    "tbl.atsd_forecast.cf.m.storeFileCount" : 0,
    "tbl.atsd_join.cf.c.staticBloomSizeKB" : 0,
    "tbl.atsd_forecast.cf.m.memstoreSizeMB" : 0,
    "tbl.atsd_nmon.cf.c.storeFileSizeMB" : 0,
    "tbl.atsd_user.cf.c.memstoreSizeMB" : 0,
    "tbl.atsd_entity.cf.t.storeFileSizeMB" : 0,
    "tbl.atsd_metric.cf.t.storeFileIndexSizeMB" : 0,
    "tbl.atsd_message.cf.e.storeFileSizeMB" : 0,
    "memstoreSizeMB" : 2585,
    "tbl.atsd_calendar.cf.c.staticBloomSizeKB" : 0,
    "tbl.atsd_rule_alert.cf.r.storeFileCount" : 0,
    "tbl.atsd_rule.cf.f.staticBloomSizeKB" : 0,
    "tbl.atsd_forecast_settings.cf.f.memstoreSizeMB" : 0,
    "tbl.atsd_d.region.3e3c21ca8e370eaeba45cc4da0af2a95.writerequestcount" : 97173,
    "compactionBlockReadCacheHitCnt" : 0,
    "tbl.atsd_d.region.1bc65979589989b6a6548b0282b46630.writerequestcount" : 153262,
    "tbl.atsd_d.region.878d77be909938b5c07efd2ddef94378.writerequestcount" : 91782,
    "tbl.atsd_nmon_uarg_data.cf.c.storeFileIndexSizeMB" : 0,
    "tbl.atsd_counter.cf.type.staticBloomSizeKB" : 0,
    "tbl.atsd_message.cf.e.storeFileIndexSizeMB" : 0,
    "tbl.atsd_failure.cf.c.staticIndexSizeKB" : 0,
    "tbl.atsd_entity_lookup.cf.c.storeFileCount" : 0,
    "tbl.atsd_failure.cf.c.storeFileSizeMB" : 0,
    "tbl.atsd_portal_config.cf.c.staticIndexSizeKB" : 0,
    "tbl.atsd_option.cf.o.memstoreSizeMB" : 0,
    "tbl.atsd_counter.cf.type.bt.Data.blockCacheSize" : 0,
    "tbl.atsd_message.cf.c.staticIndexSizeKB" : 0,
    "tbl.atsd_metric.cf.i.memstoreSizeMB" : 0,
    "compactionBlockReadCnt" : 3821,
    "tbl.atsd_d.region.52ae70a00c3d4c78e8413c788e14fff1.multiput_NumOps" : 0,
    "tbl.atsd_d.region.52ae70a00c3d4c78e8413c788e14fff1.multiput_AvgTime" : 0,
    "tbl.atsd_d.region.52ae70a00c3d4c78e8413c788e14fff1.multiput_MinTime" : 1,
    "tbl.atsd_d.region.52ae70a00c3d4c78e8413c788e14fff1.multiput_MaxTime" : 2,
    "tbl.atsd_d.cf.r.blockCacheSize" : 2616160,
    "tbl.atsd_nmon_df_data.cf.c.memstoreSizeMB" : 0,
    "storeFileCount.max" : 8,
    "tbl.atsd_message.cf.c.storeFileCount" : 0,
    "tbl.atsd_sql.cf.t.storeFileCount" : 0,
    "tbl.atsd_tag.cf.v.n.staticBloomSizeKB" : 0,
    "tbl.atsd_d.cf.r.bt.Index.compactionReadNumOps" : 1,
    "tbl.atsd_d.cf.r.bt.Index.compactionReadAvgTime" : 594273,
    "tbl.atsd_d.cf.r.bt.Index.compactionReadMinTime" : 266233,
    "tbl.atsd_d.cf.r.bt.Index.compactionReadMaxTime" : 709721,
    "tbl..META..cf.info.flushSize" : 29888,
    "tbl.atsd_d.cf.r.staticBloomSizeKB" : 0,
    "tbl.atsd_failure.cf.c.storeFileIndexSizeMB" : 0,
    "tbl.atsd_entity_lookup.cf.c.storeFileIndexSizeMB" : 0,
    "tbl.atsd_entity_group.region.092ec05e574de7a11b1d827782b9c232.readrequestcount" : 1122,
    "tbl.atsd_counter.cf.type.flushSize" : 344,
    "tbl.atsd_nmon_uarg_data.cf.c.storeFileCount" : 0,
    "tbl.atsd_forecast.cf.f.storeFileCount" : 0,
    "tbl.testtable.cf.colfam.staticBloomSizeKB" : 0,
    "tbl.atsd_d.cf.r.compactionBlockReadCnt" : 3821,
    "bt.Index.blockCacheSize" : 658128,
    "tbl.atsd_forecast_settings.cf.f.staticIndexSizeKB" : 0,
    "tbl.atsd_d.cf.r.nextsize" : 3872,
    "tbl..META..region.1028785192.readrequestcount" : 1589,
    "tbl..META..cf.info.nextsize" : 0,
    "tbl..META..region.1028785192.get_NumOps" : 0,
    "tbl..META..region.1028785192.get_AvgTime" : 0,
    "tbl..META..region.1028785192.get_MinTime" : 0,
    "tbl..META..region.1028785192.get_MaxTime" : 0,
    "tbl.atsd_rule_threshold.cf.c.storeFileIndexSizeMB" : 0,
    "tbl.atsd_d.cf.r.bt.Data.compactionBlockReadCacheMissCnt" : 3820,
    "tbl.atsd_d.region.cf78a14af314548fdccf5454f5353089.writerequestcount" : 61824,
    "tbl.-ROOT-.region.70236052.readrequestcount" : 43,
    "tbl.atsd_tag.cf.v.i.storeFileSizeMB" : 0,
    "tbl.atsd_message_type.cf.n.storeFileCount" : 0,
    "tbl.atsd_user.cf.c.storeFileCount" : 1,
    "tbl.atsd_export_job.cf.c.storeFileIndexSizeMB" : 0,
    "tbl.atsd_tag.cf.k.n.staticIndexSizeKB" : 0,
    "tbl.atsd_d.region.7d449171565c8c33eee07f64e77cce2b.multiput_NumOps" : 0,
    "tbl.atsd_d.region.7d449171565c8c33eee07f64e77cce2b.multiput_AvgTime" : 0,
    "tbl.atsd_d.region.7d449171565c8c33eee07f64e77cce2b.multiput_MinTime" : 1,
    "tbl.atsd_d.region.7d449171565c8c33eee07f64e77cce2b.multiput_MaxTime" : 2,
    "fsBlockReadCnt" : 0,
    "tbl.atsd_notification.cf.c.staticIndexSizeKB" : 0,
    "tbl.atsd_metric.cf.n.bt.Data.blockCacheSize" : 5560,
    "storeFileIndexSizeMB.max" : 0,
    "tbl.atsd_d.region.23349eb907cf6d361b4b2c4eebfdb560.writerequestcount" : 91791,
    "tbl.atsd_metric.cf.t.staticBloomSizeKB" : 0,
    "storeFileSizeMB.max" : 10318,
    "tbl.atsd_delete_task.cf.t.storeFileSizeMB" : 0,
    "tbl.-ROOT-.cf.info.storeFileSizeMB" : 0,
    "tbl.atsd_message.cf.c.storeFileIndexSizeMB" : 0,
    "tbl.atsd_d.region.cf78a14af314548fdccf5454f5353089.multiput_NumOps" : 2,
    "tbl.atsd_d.region.cf78a14af314548fdccf5454f5353089.multiput_AvgTime" : 0,
    "tbl.atsd_d.region.cf78a14af314548fdccf5454f5353089.multiput_MinTime" : 0,
    "tbl.atsd_d.region.cf78a14af314548fdccf5454f5353089.multiput_MaxTime" : 1,
    "tbl.atsd_entity_lookup.cf.c.staticBloomSizeKB" : 0,
    "tbl.atsd_csv.cf.c.staticIndexSizeKB" : 0,
    "tbl.atsd_sql.cf.t.staticIndexSizeKB" : 0,
    "staticIndexSizeKB.max" : 6276,
    "tbl.atsd_tag.cf.k.i.staticIndexSizeKB" : 0,
    "tbl.atsd_nmon_uarg_data.cf.c.storeFileSizeMB" : 0,
    "tbl.atsd_portal_config.cf.c.storeFileSizeMB" : 0,
    "tbl.atsd_nmon.cf.c.staticBloomSizeKB" : 0,
    "tbl.atsd_forecast_settings.cf.f.staticBloomSizeKB" : 0,
    "tbl.atsd_notification.cf.c.storeFileIndexSizeMB" : 0,
    "tbl.atsd_counter.cf.type.blockCacheSize" : 0,
    "storeFileIndexSizeMB" : 0,
    "bt.Index.compactionBlockReadCacheHitCnt" : 0,
    "tbl..META..cf.info.blockCacheSize" : 66312,
    "tbl.atsd_nmon_uarg_data.cf.c.staticBloomSizeKB" : 0,
    "tbl.atsd_d.region.f10eb376ecfe39675ebd3e85c1d15652.writerequestcount" : 105845,
    "tbl.atsd_d.cf.r.bt.Index.compactionBlockReadCnt" : 1,
    "tbl.atsd_portal_config.cf.c.blockCacheSize" : 372888,
    "tbl.atsd_collection.cf.c.staticBloomSizeKB" : 0,
    "tbl.atsd_message.cf.m.memstoreSizeMB" : 0,
    "tbl.atsd_metric.cf.i.staticIndexSizeKB" : 0
  }, {
    "name" : "java.lang:type=MemoryPool,name=Par Eden Space",
    "modelerType" : "sun.management.MemoryPoolImpl",
    "Name" : "Par Eden Space",
    "Type" : "HEAP",
    "Valid" : true,
    "Usage" : {
      "committed" : 278986752,
      "init" : 278986752,
      "max" : 697958400,
      "used" : 257756256
    },
    "PeakUsage" : {
      "committed" : 278986752,
      "init" : 278986752,
      "max" : 697958400,
      "used" : 278986752
    },
    "MemoryManagerNames" : [ "ConcurrentMarkSweep", "ParNew" ],
    "UsageThresholdSupported" : false,
    "CollectionUsageThreshold" : 0,
    "CollectionUsageThresholdExceeded" : false,
    "CollectionUsageThresholdCount" : 0,
    "CollectionUsage" : {
      "committed" : 278986752,
      "init" : 278986752,
      "max" : 697958400,
      "used" : 0
    },
    "CollectionUsageThresholdSupported" : true
  }, {
    "name" : "hadoop:service=RegionServer,name=RegionServerStatistics",
    "modelerType" : "org.apache.hadoop.hbase.regionserver.metrics.RegionServerStatistics",
    "totalStaticBloomSizeKB" : 0,
    "totalStaticIndexSizeKB" : 139605,
    "blockCacheFree" : 2105145880,
    "compactionSizeNumOps" : 9,
    "compactionSizeAvgTime" : 1630386791,
    "compactionSizeMinTime" : 2996,
    "compactionSizeMaxTime" : 10833092407,
    "numPutsWithoutWAL" : 0,
    "memstoreSizeMB" : 2589,
    "regions" : 68,
    "blockCacheCount" : 63,
    "blockCacheHitRatio" : 1,
    "flushQueueSize" : 1,
    "hlogFileSizeMB" : 17529,
    "atomicIncrementTimeNumOps" : 0,
    "atomicIncrementTimeAvgTime" : 0,
    "atomicIncrementTimeMinTime" : -1,
    "atomicIncrementTimeMaxTime" : 0,
    "fsReadLatencyNumOps" : 3825,
    "fsReadLatencyAvgTime" : 0,
    "fsReadLatencyMinTime" : 0,
    "fsReadLatencyMaxTime" : 5,
    "hlogFileCount" : 25,
    "blockCacheHitCachingRatio" : 98,
    "blockCacheHitCount" : 12928,
    "mbInMemoryWithoutWAL" : 0,
    "hdfsBlocksLocalityIndex" : 100,
    "writeRequestsCount" : 3305523,
    "slowHLogAppendTimeNumOps" : 0,
    "slowHLogAppendTimeAvgTime" : 0,
    "slowHLogAppendTimeMinTime" : -1,
    "slowHLogAppendTimeMaxTime" : 0,
    "compactionTimeNumOps" : 9,
    "compactionTimeAvgTime" : 28458,
    "compactionTimeMinTime" : 133,
    "compactionTimeMaxTime" : 178106,
    "fsWriteLatencyNumOps" : 2,
    "fsWriteLatencyAvgTime" : 0,
    "fsWriteLatencyMinTime" : 0,
    "fsWriteLatencyMaxTime" : 14,
    "blockCacheSize" : 20530664,
    "readRequestsCount" : 10203,
    "rootIndexSizeKB" : 1963,
    "blockCacheHitRatioPastNPeriods" : 0,
    "fsPreadLatencyNumOps" : 0,
    "fsPreadLatencyAvgTime" : 0,
    "fsPreadLatencyMinTime" : 0,
    "fsPreadLatencyMaxTime" : 437,
    "flushTimeNumOps" : 22,
    "flushTimeAvgTime" : 0,
    "flushTimeMinTime" : 0,
    "flushTimeMaxTime" : 8,
    "checksumFailuresCount" : 0,
    "blockCacheMissCount" : 903512,
    "blockCacheHitCachingRatioPastNPeriods" : 100,
    "slowHLogAppendCount" : 0,
    "updatesBlockedSeconds" : 0,
    "fsWriteSizeNumOps" : 2,
    "fsWriteSizeAvgTime" : 913,
    "fsWriteSizeMinTime" : 39,
    "fsWriteSizeMaxTime" : 8151,
    "storefiles" : 151,
    "regionSplitFailureCount" : 0,
    "blockCacheEvictedCount" : 87,
    "updatesBlockedSecondsHighWater" : 0,
    "storefileIndexSizeMB" : 1,
    "fsSyncLatencyNumOps" : 2,
    "fsSyncLatencyAvgTime" : 0,
    "fsSyncLatencyMinTime" : 0,
    "fsSyncLatencyMaxTime" : 3531,
    "stores" : 84,
    "compactionQueueSize" : 7,
    "flushSizeNumOps" : 22,
    "flushSizeAvgTime" : 374717716,
    "flushSizeMinTime" : 168,
    "flushSizeMaxTime" : 536902296,
    "regionSplitSuccessCount" : 0,
    "fsWriteLatencyHistogram_num_ops" : 866747,
    "fsWriteLatencyHistogram_min" : 2654,
    "fsWriteLatencyHistogram_max" : 1021936579,
    "fsWriteLatencyHistogram_mean" : 229360.4,
    "fsWriteLatencyHistogram_std_dev" : 3399443.2,
    "fsWriteLatencyHistogram_median" : 161157.5,
    "fsWriteLatencyHistogram_75th_percentile" : 236358.25,
    "fsWriteLatencyHistogram_95th_percentile" : 354686.44,
    "fsWriteLatencyHistogram_99th_percentile" : 411009.1,
    "requests" : 0.0,
    "fsPreadLatencyHistogram_num_ops" : 13,
    "fsPreadLatencyHistogram_min" : 753512,
    "fsPreadLatencyHistogram_max" : 437372566,
    "fsPreadLatencyHistogram_mean" : 4.0926776E7,
    "fsPreadLatencyHistogram_std_dev" : 1.19572264E8,
    "fsPreadLatencyHistogram_median" : 2804598.0,
    "fsPreadLatencyHistogram_75th_percentile" : 1.792664E7,
    "fsPreadLatencyHistogram_95th_percentile" : 4.37372576E8,
    "fsPreadLatencyHistogram_99th_percentile" : 4.37372576E8,
    "fsReadLatencyHistogram_num_ops" : 741367,
    "fsReadLatencyHistogram_min" : 4400,
    "fsReadLatencyHistogram_max" : 543898446,
    "fsReadLatencyHistogram_mean" : 317980.4,
    "fsReadLatencyHistogram_std_dev" : 4291843.5,
    "fsReadLatencyHistogram_median" : 145618.0,
    "fsReadLatencyHistogram_75th_percentile" : 207077.25,
    "fsReadLatencyHistogram_95th_percentile" : 319776.5,
    "fsReadLatencyHistogram_99th_percentile" : 1588199.5
  }, {
    "name" : "com.sun.management:type=HotSpotDiagnostic",
    "modelerType" : "sun.management.HotSpotDiagnostic"
  }, {
    "name" : "java.lang:type=MemoryPool,name=CMS Perm Gen",
    "modelerType" : "sun.management.MemoryPoolImpl",
    "Name" : "CMS Perm Gen",
    "Type" : "NON_HEAP",
    "Valid" : true,
    "Usage" : {
      "committed" : 38866944,
      "init" : 21757952,
      "max" : 174063616,
      "used" : 23882232
    },
    "PeakUsage" : {
      "committed" : 38866944,
      "init" : 21757952,
      "max" : 174063616,
      "used" : 23882392
    },
    "MemoryManagerNames" : [ "ConcurrentMarkSweep" ],
    "UsageThreshold" : 0,
    "UsageThresholdExceeded" : false,
    "UsageThresholdCount" : 0,
    "UsageThresholdSupported" : true,
    "CollectionUsageThreshold" : 0,
    "CollectionUsageThresholdExceeded" : false,
    "CollectionUsageThresholdCount" : 0,
    "CollectionUsage" : {
      "committed" : 38866944,
      "init" : 21757952,
      "max" : 174063616,
      "used" : 23302784
    },
    "CollectionUsageThresholdSupported" : true
  }, {
    "name" : "java.lang:type=OperatingSystem",
    "modelerType" : "com.sun.management.UnixOperatingSystem",
    "OpenFileDescriptorCount" : 329,
    "MaxFileDescriptorCount" : 32768,
    "TotalSwapSpaceSize" : 34342825984,
    "FreeSwapSpaceSize" : 34342756352,
    "CommittedVirtualMemorySize" : 9450512384,
    "ProcessCpuTime" : 8425380000000,
    "FreePhysicalMemorySize" : 387031040,
    "TotalPhysicalMemorySize" : 66954280960,
    "Name" : "Linux",
    "Version" : "3.13.0-54-generic",
    "AvailableProcessors" : 12,
    "Arch" : "amd64",
    "SystemLoadAverage" : 3.05
  }, {
    "name" : "java.lang:type=MemoryPool,name=Par Survivor Space",
    "modelerType" : "sun.management.MemoryPoolImpl",
    "Name" : "Par Survivor Space",
    "Type" : "HEAP",
    "Valid" : true,
    "Usage" : {
      "committed" : 34865152,
      "init" : 34865152,
      "max" : 87228416,
      "used" : 1127176
    },
    "PeakUsage" : {
      "committed" : 34865152,
      "init" : 34865152,
      "max" : 87228416,
      "used" : 34865152
    },
    "MemoryManagerNames" : [ "ConcurrentMarkSweep", "ParNew" ],
    "UsageThresholdSupported" : false,
    "CollectionUsageThreshold" : 0,
    "CollectionUsageThresholdExceeded" : false,
    "CollectionUsageThresholdCount" : 0,
    "CollectionUsage" : {
      "committed" : 34865152,
      "init" : 34865152,
      "max" : 87228416,
      "used" : 1127176
    },
    "CollectionUsageThresholdSupported" : true
  }, {
    "name" : "JMImplementation:type=MBeanServerDelegate",
    "modelerType" : "javax.management.MBeanServerDelegate",
    "MBeanServerId" : "NURSWGHBS001_1437465981584",
    "SpecificationName" : "Java Management Extensions",
    "SpecificationVersion" : "1.4",
    "SpecificationVendor" : "Sun Microsystems",
    "ImplementationName" : "JMX",
    "ImplementationVersion" : "1.6.0_35-b35",
    "ImplementationVendor" : "Sun Microsystems"
  }, {
    "name" : "java.lang:type=MemoryManager,name=CodeCacheManager",
    "modelerType" : "sun.management.MemoryManagerImpl",
    "Name" : "CodeCacheManager",
    "Valid" : true,
    "MemoryPoolNames" : [ "Code Cache" ]
  } ]
}